[{"uur5minuten":"0:00","datum":"2018-12-01","tegenrichting":0,"hoofdrichting":0,"totaal":0,"locatie":"Bataviabrug"},{"uur5minuten":"1:00","datum":"2018-12-01","tegenrichting":0,"hoofdrichting":0,"totaal":0,"locatie":"Bataviabrug"},{"uur5minuten":"2:00","datum":"2018-12-01","tegenrichting":0,"hoofdrichting":0,"totaal":0,"locatie":"Bataviabrug"},{"uur5minuten":"3:00","datum":"2018-12-01","tegenrichting":0,"hoofdrichting":0,"totaal":0,"locatie":"Bataviabrug"},{"uur5minuten":"4:00","datum":"2018-12-01","tegenrichting":0,"hoofdrichting":0,"totaal":0,"locatie":"Bataviabrug"},{"uur5minuten":"5:00","datum":"2018-12-01","tegenrichting":0,"hoofdrichting":0,"totaal":0,"locatie":"Bataviabrug"},{"uur5minuten":"6:00","datum":"2018-12-01","tegenrichting":0,"hoofdrichting":0,"totaal":0,"locatie":"Bataviabrug"},{"uur5minuten":"7:00","datum":"2018-12-01","tegenrichting":0,"hoofdrichting":0,"totaal":0,"locatie":"Bataviabrug"},{"uur5minuten":"8:00","datum":"2018-12-01","tegenrichting":0,"hoofdrichting":0,"totaal":0,"locatie":"Bataviabrug"},{"uur5minuten":"9:00","datum":"2018-12-01","tegenrichting":0,"hoofdrichting":0,"totaal":0,"locatie":"Bataviabrug"},{"uur5minuten":"10:00","datum":"2018-12-01","tegenrichting":0,"hoofdrichting":0,"totaal":0,"locatie":"Bataviabrug"},{"uur5minuten":"11:00","datum":"2018-12-01","tegenrichting":0,"hoofdrichting":0,"totaal":0,"locatie":"Bataviabrug"},{"uur5minuten":"12:00","datum":"2018-12-01","tegenrichting":0,"hoofdrichting":0,"totaal":0,"locatie":"Bataviabrug"},{"uur5minuten":"13:00","datum":"2018-12-01","tegenrichting":0,"hoofdrichting":0,"totaal":0,"locatie":"Bataviabrug"},{"uur5minuten":"14:00","datum":"2018-12-01","tegenrichting":0,"hoofdrichting":0,"totaal":0,"locatie":"Bataviabrug"},{"uur5minuten":"15:00","datum":"2018-12-01","tegenrichting":0,"hoofdrichting":0,"totaal":0,"locatie":"Bataviabrug"},{"uur5minuten":"16:00","datum":"2018-12-01","tegenrichting":0,"hoofdrichting":0,"totaal":0,"locatie":"Bataviabrug"},{"uur5minuten":"17:00","datum":"2018-12-01","tegenrichting":0,"hoofdrichting":0,"totaal":0,"locatie":"Bataviabrug"},{"uur5minuten":"18:00","datum":"2018-12-01","tegenrichting":0,"hoofdrichting":0,"totaal":0,"locatie":"Bataviabrug"},{"uur5minuten":"19:00","datum":"2018-12-01","tegenrichting":0,"hoofdrichting":0,"totaal":0,"locatie":"Bataviabrug"},{"uur5minuten":"20:00","datum":"2018-12-01","tegenrichting":0,"hoofdrichting":0,"totaal":0,"locatie":"Bataviabrug"},{"uur5minuten":"21:00","datum":"2018-12-01","tegenrichting":0,"hoofdrichting":0,"totaal":0,"locatie":"Bataviabrug"},{"uur5minuten":"22:00","datum":"2018-12-01","tegenrichting":0,"hoofdrichting":0,"totaal":0,"locatie":"Bataviabrug"},{"uur5minuten":"23:00","datum":"2018-12-01","tegenrichting":0,"hoofdrichting":0,"totaal":0,"locatie":"Bataviabrug"},{"uur5minuten":"0:00","datum":"2018-12-02","tegenrichting":0,"hoofdrichting":0,"totaal":0,"locatie":"Bataviabrug"},{"uur5minuten":"1:00","datum":"2018-12-02","tegenrichting":0,"hoofdrichting":0,"totaal":0,"locatie":"Bataviabrug"},{"uur5minuten":"2:00","datum":"2018-12-02","tegenrichting":0,"hoofdrichting":0,"totaal":0,"locatie":"Bataviabrug"},{"uur5minuten":"3:00","datum":"2018-12-02","tegenrichting":0,"hoofdrichting":0,"totaal":0,"locatie":"Bataviabrug"},{"uur5minuten":"4:00","datum":"2018-12-02","tegenrichting":0,"hoofdrichting":0,"totaal":0,"locatie":"Bataviabrug"},{"uur5minuten":"5:00","datum":"2018-12-02","tegenrichting":0,"hoofdrichting":0,"totaal":0,"locatie":"Bataviabrug"},{"uur5minuten":"6:00","datum":"2018-12-02","tegenrichting":0,"hoofdrichting":0,"totaal":0,"locatie":"Bataviabrug"},{"uur5minuten":"7:00","datum":"2018-12-02","tegenrichting":0,"hoofdrichting":0,"totaal":0,"locatie":"Bataviabrug"},{"uur5minuten":"8:00","datum":"2018-12-02","tegenrichting":0,"hoofdrichting":0,"totaal":0,"locatie":"Bataviabrug"},{"uur5minuten":"9:00","datum":"2018-12-02","tegenrichting":0,"hoofdrichting":0,"totaal":0,"locatie":"Bataviabrug"},{"uur5minuten":"10:00","datum":"2018-12-02","tegenrichting":0,"hoofdrichting":0,"totaal":0,"locatie":"Bataviabrug"},{"uur5minuten":"11:00","datum":"2018-12-02","tegenrichting":0,"hoofdrichting":0,"totaal":0,"locatie":"Bataviabrug"},{"uur5minuten":"12:00","datum":"2018-12-02","tegenrichting":0,"hoofdrichting":0,"totaal":0,"locatie":"Bataviabrug"},{"uur5minuten":"13:00","datum":"2018-12-02","tegenrichting":0,"hoofdrichting":0,"totaal":0,"locatie":"Bataviabrug"},{"uur5minuten":"14:00","datum":"2018-12-02","tegenrichting":0,"hoofdrichting":0,"totaal":0,"locatie":"Bataviabrug"},{"uur5minuten":"15:00","datum":"2018-12-02","tegenrichting":0,"hoofdrichting":0,"totaal":0,"locatie":"Bataviabrug"},{"uur5minuten":"16:00","datum":"2018-12-02","tegenrichting":0,"hoofdrichting":0,"totaal":0,"locatie":"Bataviabrug"},{"uur5minuten":"17:00","datum":"2018-12-02","tegenrichting":0,"hoofdrichting":0,"totaal":0,"locatie":"Bataviabrug"},{"uur5minuten":"18:00","datum":"2018-12-02","tegenrichting":0,"hoofdrichting":0,"totaal":0,"locatie":"Bataviabrug"},{"uur5minuten":"19:00","datum":"2018-12-02","tegenrichting":0,"hoofdrichting":0,"totaal":0,"locatie":"Bataviabrug"},{"uur5minuten":"20:00","datum":"2018-12-02","tegenrichting":0,"hoofdrichting":0,"totaal":0,"locatie":"Bataviabrug"},{"uur5minuten":"21:00","datum":"2018-12-02","tegenrichting":0,"hoofdrichting":0,"totaal":0,"locatie":"Bataviabrug"},{"uur5minuten":"22:00","datum":"2018-12-02","tegenrichting":0,"hoofdrichting":0,"totaal":0,"locatie":"Bataviabrug"},{"uur5minuten":"23:00","datum":"2018-12-02","tegenrichting":0,"hoofdrichting":0,"totaal":0,"locatie":"Bataviabrug"},{"uur5minuten":"0:00","datum":"2018-12-03","tegenrichting":0,"hoofdrichting":0,"totaal":0,"locatie":"Bataviabrug"},{"uur5minuten":"1:00","datum":"2018-12-03","tegenrichting":0,"hoofdrichting":0,"totaal":0,"locatie":"Bataviabrug"},{"uur5minuten":"2:00","datum":"2018-12-03","tegenrichting":0,"hoofdrichting":0,"totaal":0,"locatie":"Bataviabrug"},{"uur5minuten":"3:00","datum":"2018-12-03","tegenrichting":0,"hoofdrichting":0,"totaal":0,"locatie":"Bataviabrug"},{"uur5minuten":"4:00","datum":"2018-12-03","tegenrichting":0,"hoofdrichting":0,"totaal":0,"locatie":"Bataviabrug"},{"uur5minuten":"5:00","datum":"2018-12-03","tegenrichting":0,"hoofdrichting":0,"totaal":0,"locatie":"Bataviabrug"},{"uur5minuten":"6:00","datum":"2018-12-03","tegenrichting":0,"hoofdrichting":0,"totaal":0,"locatie":"Bataviabrug"},{"uur5minuten":"7:00","datum":"2018-12-03","tegenrichting":0,"hoofdrichting":0,"totaal":0,"locatie":"Bataviabrug"},{"uur5minuten":"8:00","datum":"2018-12-03","tegenrichting":0,"hoofdrichting":0,"totaal":0,"locatie":"Bataviabrug"},{"uur5minuten":"9:00","datum":"2018-12-03","tegenrichting":0,"hoofdrichting":0,"totaal":0,"locatie":"Bataviabrug"},{"uur5minuten":"10:00","datum":"2018-12-03","tegenrichting":0,"hoofdrichting":0,"totaal":0,"locatie":"Bataviabrug"},{"uur5minuten":"11:00","datum":"2018-12-03","tegenrichting":0,"hoofdrichting":0,"totaal":0,"locatie":"Bataviabrug"},{"uur5minuten":"12:00","datum":"2018-12-03","tegenrichting":0,"hoofdrichting":0,"totaal":0,"locatie":"Bataviabrug"},{"uur5minuten":"13:00","datum":"2018-12-03","tegenrichting":0,"hoofdrichting":0,"totaal":0,"locatie":"Bataviabrug"},{"uur5minuten":"14:00","datum":"2018-12-03","tegenrichting":0,"hoofdrichting":0,"totaal":0,"locatie":"Bataviabrug"},{"uur5minuten":"15:00","datum":"2018-12-03","tegenrichting":0,"hoofdrichting":0,"totaal":0,"locatie":"Bataviabrug"},{"uur5minuten":"16:00","datum":"2018-12-03","tegenrichting":0,"hoofdrichting":0,"totaal":0,"locatie":"Bataviabrug"},{"uur5minuten":"17:00","datum":"2018-12-03","tegenrichting":0,"hoofdrichting":0,"totaal":0,"locatie":"Bataviabrug"},{"uur5minuten":"18:00","datum":"2018-12-03","tegenrichting":0,"hoofdrichting":0,"totaal":0,"locatie":"Bataviabrug"},{"uur5minuten":"19:00","datum":"2018-12-03","tegenrichting":0,"hoofdrichting":0,"totaal":0,"locatie":"Bataviabrug"},{"uur5minuten":"20:00","datum":"2018-12-03","tegenrichting":0,"hoofdrichting":0,"totaal":0,"locatie":"Bataviabrug"},{"uur5minuten":"21:00","datum":"2018-12-03","tegenrichting":0,"hoofdrichting":0,"totaal":0,"locatie":"Bataviabrug"},{"uur5minuten":"22:00","datum":"2018-12-03","tegenrichting":0,"hoofdrichting":0,"totaal":0,"locatie":"Bataviabrug"},{"uur5minuten":"23:00","datum":"2018-12-03","tegenrichting":0,"hoofdrichting":0,"totaal":0,"locatie":"Bataviabrug"},{"uur5minuten":"0:00","datum":"2018-12-04","tegenrichting":0,"hoofdrichting":0,"totaal":0,"locatie":"Bataviabrug"},{"uur5minuten":"1:00","datum":"2018-12-04","tegenrichting":0,"hoofdrichting":0,"totaal":0,"locatie":"Bataviabrug"},{"uur5minuten":"2:00","datum":"2018-12-04","tegenrichting":0,"hoofdrichting":0,"totaal":0,"locatie":"Bataviabrug"},{"uur5minuten":"3:00","datum":"2018-12-04","tegenrichting":0,"hoofdrichting":0,"totaal":0,"locatie":"Bataviabrug"},{"uur5minuten":"4:00","datum":"2018-12-04","tegenrichting":0,"hoofdrichting":0,"totaal":0,"locatie":"Bataviabrug"},{"uur5minuten":"5:00","datum":"2018-12-04","tegenrichting":0,"hoofdrichting":0,"totaal":0,"locatie":"Bataviabrug"},{"uur5minuten":"6:00","datum":"2018-12-04","tegenrichting":0,"hoofdrichting":0,"totaal":0,"locatie":"Bataviabrug"},{"uur5minuten":"7:00","datum":"2018-12-04","tegenrichting":0,"hoofdrichting":0,"totaal":0,"locatie":"Bataviabrug"},{"uur5minuten":"8:00","datum":"2018-12-04","tegenrichting":0,"hoofdrichting":0,"totaal":0,"locatie":"Bataviabrug"},{"uur5minuten":"9:00","datum":"2018-12-04","tegenrichting":0,"hoofdrichting":0,"totaal":0,"locatie":"Bataviabrug"},{"uur5minuten":"10:00","datum":"2018-12-04","tegenrichting":0,"hoofdrichting":0,"totaal":0,"locatie":"Bataviabrug"},{"uur5minuten":"11:00","datum":"2018-12-04","tegenrichting":0,"hoofdrichting":0,"totaal":0,"locatie":"Bataviabrug"},{"uur5minuten":"12:00","datum":"2018-12-04","tegenrichting":0,"hoofdrichting":0,"totaal":0,"locatie":"Bataviabrug"},{"uur5minuten":"13:00","datum":"2018-12-04","tegenrichting":0,"hoofdrichting":0,"totaal":0,"locatie":"Bataviabrug"},{"uur5minuten":"14:00","datum":"2018-12-04","tegenrichting":0,"hoofdrichting":0,"totaal":0,"locatie":"Bataviabrug"},{"uur5minuten":"15:00","datum":"2018-12-04","tegenrichting":0,"hoofdrichting":0,"totaal":0,"locatie":"Bataviabrug"},{"uur5minuten":"16:00","datum":"2018-12-04","tegenrichting":0,"hoofdrichting":0,"totaal":0,"locatie":"Bataviabrug"},{"uur5minuten":"17:00","datum":"2018-12-04","tegenrichting":0,"hoofdrichting":0,"totaal":0,"locatie":"Bataviabrug"},{"uur5minuten":"18:00","datum":"2018-12-04","tegenrichting":0,"hoofdrichting":0,"totaal":0,"locatie":"Bataviabrug"},{"uur5minuten":"19:00","datum":"2018-12-04","tegenrichting":0,"hoofdrichting":0,"totaal":0,"locatie":"Bataviabrug"},{"uur5minuten":"20:00","datum":"2018-12-04","tegenrichting":0,"hoofdrichting":0,"totaal":0,"locatie":"Bataviabrug"},{"uur5minuten":"21:00","datum":"2018-12-04","tegenrichting":0,"hoofdrichting":0,"totaal":0,"locatie":"Bataviabrug"},{"uur5minuten":"22:00","datum":"2018-12-04","tegenrichting":0,"hoofdrichting":0,"totaal":0,"locatie":"Bataviabrug"},{"uur5minuten":"23:00","datum":"2018-12-04","tegenrichting":0,"hoofdrichting":0,"totaal":0,"locatie":"Bataviabrug"},{"uur5minuten":"0:00","datum":"2018-12-05","tegenrichting":0,"hoofdrichting":0,"totaal":0,"locatie":"Bataviabrug"},{"uur5minuten":"1:00","datum":"2018-12-05","tegenrichting":0,"hoofdrichting":0,"totaal":0,"locatie":"Bataviabrug"},{"uur5minuten":"2:00","datum":"2018-12-05","tegenrichting":0,"hoofdrichting":0,"totaal":0,"locatie":"Bataviabrug"},{"uur5minuten":"3:00","datum":"2018-12-05","tegenrichting":0,"hoofdrichting":0,"totaal":0,"locatie":"Bataviabrug"},{"uur5minuten":"4:00","datum":"2018-12-05","tegenrichting":0,"hoofdrichting":0,"totaal":0,"locatie":"Bataviabrug"},{"uur5minuten":"5:00","datum":"2018-12-05","tegenrichting":0,"hoofdrichting":0,"totaal":0,"locatie":"Bataviabrug"},{"uur5minuten":"6:00","datum":"2018-12-05","tegenrichting":0,"hoofdrichting":0,"totaal":0,"locatie":"Bataviabrug"},{"uur5minuten":"7:00","datum":"2018-12-05","tegenrichting":0,"hoofdrichting":0,"totaal":0,"locatie":"Bataviabrug"},{"uur5minuten":"8:00","datum":"2018-12-05","tegenrichting":0,"hoofdrichting":0,"totaal":0,"locatie":"Bataviabrug"},{"uur5minuten":"9:00","datum":"2018-12-05","tegenrichting":0,"hoofdrichting":0,"totaal":0,"locatie":"Bataviabrug"},{"uur5minuten":"10:00","datum":"2018-12-05","tegenrichting":0,"hoofdrichting":0,"totaal":0,"locatie":"Bataviabrug"},{"uur5minuten":"11:00","datum":"2018-12-05","tegenrichting":0,"hoofdrichting":0,"totaal":0,"locatie":"Bataviabrug"},{"uur5minuten":"12:00","datum":"2018-12-05","tegenrichting":0,"hoofdrichting":0,"totaal":0,"locatie":"Bataviabrug"},{"uur5minuten":"13:00","datum":"2018-12-05","tegenrichting":0,"hoofdrichting":0,"totaal":0,"locatie":"Bataviabrug"},{"uur5minuten":"14:00","datum":"2018-12-05","tegenrichting":0,"hoofdrichting":0,"totaal":0,"locatie":"Bataviabrug"},{"uur5minuten":"15:00","datum":"2018-12-05","tegenrichting":0,"hoofdrichting":0,"totaal":0,"locatie":"Bataviabrug"},{"uur5minuten":"16:00","datum":"2018-12-05","tegenrichting":0,"hoofdrichting":0,"totaal":0,"locatie":"Bataviabrug"},{"uur5minuten":"17:00","datum":"2018-12-05","tegenrichting":0,"hoofdrichting":0,"totaal":0,"locatie":"Bataviabrug"},{"uur5minuten":"18:00","datum":"2018-12-05","tegenrichting":0,"hoofdrichting":0,"totaal":0,"locatie":"Bataviabrug"},{"uur5minuten":"19:00","datum":"2018-12-05","tegenrichting":0,"hoofdrichting":0,"totaal":0,"locatie":"Bataviabrug"},{"uur5minuten":"20:00","datum":"2018-12-05","tegenrichting":0,"hoofdrichting":0,"totaal":0,"locatie":"Bataviabrug"},{"uur5minuten":"21:00","datum":"2018-12-05","tegenrichting":0,"hoofdrichting":0,"totaal":0,"locatie":"Bataviabrug"},{"uur5minuten":"22:00","datum":"2018-12-05","tegenrichting":0,"hoofdrichting":0,"totaal":0,"locatie":"Bataviabrug"},{"uur5minuten":"23:00","datum":"2018-12-05","tegenrichting":0,"hoofdrichting":0,"totaal":0,"locatie":"Bataviabrug"},{"uur5minuten":"0:00","datum":"2018-12-06","tegenrichting":0,"hoofdrichting":0,"totaal":0,"locatie":"Bataviabrug"},{"uur5minuten":"1:00","datum":"2018-12-06","tegenrichting":0,"hoofdrichting":0,"totaal":0,"locatie":"Bataviabrug"},{"uur5minuten":"2:00","datum":"2018-12-06","tegenrichting":0,"hoofdrichting":0,"totaal":0,"locatie":"Bataviabrug"},{"uur5minuten":"3:00","datum":"2018-12-06","tegenrichting":0,"hoofdrichting":0,"totaal":0,"locatie":"Bataviabrug"},{"uur5minuten":"4:00","datum":"2018-12-06","tegenrichting":0,"hoofdrichting":0,"totaal":0,"locatie":"Bataviabrug"},{"uur5minuten":"5:00","datum":"2018-12-06","tegenrichting":0,"hoofdrichting":0,"totaal":0,"locatie":"Bataviabrug"},{"uur5minuten":"6:00","datum":"2018-12-06","tegenrichting":0,"hoofdrichting":0,"totaal":0,"locatie":"Bataviabrug"},{"uur5minuten":"7:00","datum":"2018-12-06","tegenrichting":0,"hoofdrichting":0,"totaal":0,"locatie":"Bataviabrug"},{"uur5minuten":"8:00","datum":"2018-12-06","tegenrichting":0,"hoofdrichting":0,"totaal":0,"locatie":"Bataviabrug"},{"uur5minuten":"9:00","datum":"2018-12-06","tegenrichting":0,"hoofdrichting":0,"totaal":0,"locatie":"Bataviabrug"},{"uur5minuten":"10:00","datum":"2018-12-06","tegenrichting":0,"hoofdrichting":0,"totaal":0,"locatie":"Bataviabrug"},{"uur5minuten":"11:00","datum":"2018-12-06","tegenrichting":0,"hoofdrichting":0,"totaal":0,"locatie":"Bataviabrug"},{"uur5minuten":"12:00","datum":"2018-12-06","tegenrichting":0,"hoofdrichting":0,"totaal":0,"locatie":"Bataviabrug"},{"uur5minuten":"13:00","datum":"2018-12-06","tegenrichting":0,"hoofdrichting":0,"totaal":0,"locatie":"Bataviabrug"},{"uur5minuten":"14:00","datum":"2018-12-06","tegenrichting":0,"hoofdrichting":0,"totaal":0,"locatie":"Bataviabrug"},{"uur5minuten":"15:00","datum":"2018-12-06","tegenrichting":0,"hoofdrichting":0,"totaal":0,"locatie":"Bataviabrug"},{"uur5minuten":"16:00","datum":"2018-12-06","tegenrichting":0,"hoofdrichting":0,"totaal":0,"locatie":"Bataviabrug"},{"uur5minuten":"17:00","datum":"2018-12-06","tegenrichting":0,"hoofdrichting":0,"totaal":0,"locatie":"Bataviabrug"},{"uur5minuten":"18:00","datum":"2018-12-06","tegenrichting":0,"hoofdrichting":0,"totaal":0,"locatie":"Bataviabrug"},{"uur5minuten":"19:00","datum":"2018-12-06","tegenrichting":0,"hoofdrichting":0,"totaal":0,"locatie":"Bataviabrug"},{"uur5minuten":"20:00","datum":"2018-12-06","tegenrichting":0,"hoofdrichting":0,"totaal":0,"locatie":"Bataviabrug"},{"uur5minuten":"21:00","datum":"2018-12-06","tegenrichting":0,"hoofdrichting":0,"totaal":0,"locatie":"Bataviabrug"},{"uur5minuten":"22:00","datum":"2018-12-06","tegenrichting":0,"hoofdrichting":0,"totaal":0,"locatie":"Bataviabrug"},{"uur5minuten":"23:00","datum":"2018-12-06","tegenrichting":0,"hoofdrichting":0,"totaal":0,"locatie":"Bataviabrug"},{"uur5minuten":"0:00","datum":"2018-12-07","tegenrichting":0,"hoofdrichting":0,"totaal":0,"locatie":"Bataviabrug"},{"uur5minuten":"1:00","datum":"2018-12-07","tegenrichting":0,"hoofdrichting":0,"totaal":0,"locatie":"Bataviabrug"},{"uur5minuten":"2:00","datum":"2018-12-07","tegenrichting":0,"hoofdrichting":0,"totaal":0,"locatie":"Bataviabrug"},{"uur5minuten":"3:00","datum":"2018-12-07","tegenrichting":0,"hoofdrichting":0,"totaal":0,"locatie":"Bataviabrug"},{"uur5minuten":"4:00","datum":"2018-12-07","tegenrichting":0,"hoofdrichting":0,"totaal":0,"locatie":"Bataviabrug"},{"uur5minuten":"5:00","datum":"2018-12-07","tegenrichting":0,"hoofdrichting":0,"totaal":0,"locatie":"Bataviabrug"},{"uur5minuten":"6:00","datum":"2018-12-07","tegenrichting":0,"hoofdrichting":0,"totaal":0,"locatie":"Bataviabrug"},{"uur5minuten":"7:00","datum":"2018-12-07","tegenrichting":0,"hoofdrichting":0,"totaal":0,"locatie":"Bataviabrug"},{"uur5minuten":"8:00","datum":"2018-12-07","tegenrichting":0,"hoofdrichting":0,"totaal":0,"locatie":"Bataviabrug"},{"uur5minuten":"9:00","datum":"2018-12-07","tegenrichting":0,"hoofdrichting":0,"totaal":0,"locatie":"Bataviabrug"},{"uur5minuten":"10:00","datum":"2018-12-07","tegenrichting":0,"hoofdrichting":0,"totaal":0,"locatie":"Bataviabrug"},{"uur5minuten":"11:00","datum":"2018-12-07","tegenrichting":0,"hoofdrichting":0,"totaal":0,"locatie":"Bataviabrug"},{"uur5minuten":"12:00","datum":"2018-12-07","tegenrichting":0,"hoofdrichting":0,"totaal":0,"locatie":"Bataviabrug"},{"uur5minuten":"13:00","datum":"2018-12-07","tegenrichting":0,"hoofdrichting":0,"totaal":0,"locatie":"Bataviabrug"},{"uur5minuten":"14:00","datum":"2018-12-07","tegenrichting":0,"hoofdrichting":0,"totaal":0,"locatie":"Bataviabrug"},{"uur5minuten":"15:00","datum":"2018-12-07","tegenrichting":0,"hoofdrichting":0,"totaal":0,"locatie":"Bataviabrug"},{"uur5minuten":"16:00","datum":"2018-12-07","tegenrichting":0,"hoofdrichting":0,"totaal":0,"locatie":"Bataviabrug"},{"uur5minuten":"17:00","datum":"2018-12-07","tegenrichting":0,"hoofdrichting":0,"totaal":0,"locatie":"Bataviabrug"},{"uur5minuten":"18:00","datum":"2018-12-07","tegenrichting":0,"hoofdrichting":0,"totaal":0,"locatie":"Bataviabrug"},{"uur5minuten":"19:00","datum":"2018-12-07","tegenrichting":0,"hoofdrichting":0,"totaal":0,"locatie":"Bataviabrug"},{"uur5minuten":"20:00","datum":"2018-12-07","tegenrichting":0,"hoofdrichting":0,"totaal":0,"locatie":"Bataviabrug"},{"uur5minuten":"21:00","datum":"2018-12-07","tegenrichting":0,"hoofdrichting":0,"totaal":0,"locatie":"Bataviabrug"},{"uur5minuten":"22:00","datum":"2018-12-07","tegenrichting":0,"hoofdrichting":0,"totaal":0,"locatie":"Bataviabrug"},{"uur5minuten":"23:00","datum":"2018-12-07","tegenrichting":0,"hoofdrichting":0,"totaal":0,"locatie":"Bataviabrug"},{"uur5minuten":"0:00","datum":"2018-12-08","tegenrichting":0,"hoofdrichting":0,"totaal":0,"locatie":"Bataviabrug"},{"uur5minuten":"1:00","datum":"2018-12-08","tegenrichting":0,"hoofdrichting":0,"totaal":0,"locatie":"Bataviabrug"},{"uur5minuten":"2:00","datum":"2018-12-08","tegenrichting":0,"hoofdrichting":0,"totaal":0,"locatie":"Bataviabrug"},{"uur5minuten":"3:00","datum":"2018-12-08","tegenrichting":0,"hoofdrichting":0,"totaal":0,"locatie":"Bataviabrug"},{"uur5minuten":"4:00","datum":"2018-12-08","tegenrichting":0,"hoofdrichting":0,"totaal":0,"locatie":"Bataviabrug"},{"uur5minuten":"5:00","datum":"2018-12-08","tegenrichting":0,"hoofdrichting":0,"totaal":0,"locatie":"Bataviabrug"},{"uur5minuten":"6:00","datum":"2018-12-08","tegenrichting":0,"hoofdrichting":0,"totaal":0,"locatie":"Bataviabrug"},{"uur5minuten":"7:00","datum":"2018-12-08","tegenrichting":0,"hoofdrichting":0,"totaal":0,"locatie":"Bataviabrug"},{"uur5minuten":"8:00","datum":"2018-12-08","tegenrichting":0,"hoofdrichting":0,"totaal":0,"locatie":"Bataviabrug"},{"uur5minuten":"9:00","datum":"2018-12-08","tegenrichting":0,"hoofdrichting":0,"totaal":0,"locatie":"Bataviabrug"},{"uur5minuten":"10:00","datum":"2018-12-08","tegenrichting":0,"hoofdrichting":0,"totaal":0,"locatie":"Bataviabrug"},{"uur5minuten":"11:00","datum":"2018-12-08","tegenrichting":0,"hoofdrichting":0,"totaal":0,"locatie":"Bataviabrug"},{"uur5minuten":"12:00","datum":"2018-12-08","tegenrichting":0,"hoofdrichting":0,"totaal":0,"locatie":"Bataviabrug"},{"uur5minuten":"13:00","datum":"2018-12-08","tegenrichting":0,"hoofdrichting":0,"totaal":0,"locatie":"Bataviabrug"},{"uur5minuten":"14:00","datum":"2018-12-08","tegenrichting":0,"hoofdrichting":0,"totaal":0,"locatie":"Bataviabrug"},{"uur5minuten":"15:00","datum":"2018-12-08","tegenrichting":0,"hoofdrichting":0,"totaal":0,"locatie":"Bataviabrug"},{"uur5minuten":"16:00","datum":"2018-12-08","tegenrichting":0,"hoofdrichting":0,"totaal":0,"locatie":"Bataviabrug"},{"uur5minuten":"17:00","datum":"2018-12-08","tegenrichting":0,"hoofdrichting":0,"totaal":0,"locatie":"Bataviabrug"},{"uur5minuten":"18:00","datum":"2018-12-08","tegenrichting":0,"hoofdrichting":0,"totaal":0,"locatie":"Bataviabrug"},{"uur5minuten":"19:00","datum":"2018-12-08","tegenrichting":0,"hoofdrichting":0,"totaal":0,"locatie":"Bataviabrug"},{"uur5minuten":"20:00","datum":"2018-12-08","tegenrichting":0,"hoofdrichting":0,"totaal":0,"locatie":"Bataviabrug"},{"uur5minuten":"21:00","datum":"2018-12-08","tegenrichting":0,"hoofdrichting":0,"totaal":0,"locatie":"Bataviabrug"},{"uur5minuten":"22:00","datum":"2018-12-08","tegenrichting":0,"hoofdrichting":0,"totaal":0,"locatie":"Bataviabrug"},{"uur5minuten":"23:00","datum":"2018-12-08","tegenrichting":0,"hoofdrichting":0,"totaal":0,"locatie":"Bataviabrug"},{"uur5minuten":"0:00","datum":"2018-12-09","tegenrichting":0,"hoofdrichting":0,"totaal":0,"locatie":"Bataviabrug"},{"uur5minuten":"1:00","datum":"2018-12-09","tegenrichting":0,"hoofdrichting":0,"totaal":0,"locatie":"Bataviabrug"},{"uur5minuten":"2:00","datum":"2018-12-09","tegenrichting":0,"hoofdrichting":0,"totaal":0,"locatie":"Bataviabrug"},{"uur5minuten":"3:00","datum":"2018-12-09","tegenrichting":0,"hoofdrichting":0,"totaal":0,"locatie":"Bataviabrug"},{"uur5minuten":"4:00","datum":"2018-12-09","tegenrichting":0,"hoofdrichting":0,"totaal":0,"locatie":"Bataviabrug"},{"uur5minuten":"5:00","datum":"2018-12-09","tegenrichting":0,"hoofdrichting":0,"totaal":0,"locatie":"Bataviabrug"},{"uur5minuten":"6:00","datum":"2018-12-09","tegenrichting":0,"hoofdrichting":0,"totaal":0,"locatie":"Bataviabrug"},{"uur5minuten":"7:00","datum":"2018-12-09","tegenrichting":0,"hoofdrichting":0,"totaal":0,"locatie":"Bataviabrug"},{"uur5minuten":"8:00","datum":"2018-12-09","tegenrichting":0,"hoofdrichting":0,"totaal":0,"locatie":"Bataviabrug"},{"uur5minuten":"9:00","datum":"2018-12-09","tegenrichting":0,"hoofdrichting":0,"totaal":0,"locatie":"Bataviabrug"},{"uur5minuten":"10:00","datum":"2018-12-09","tegenrichting":0,"hoofdrichting":0,"totaal":0,"locatie":"Bataviabrug"},{"uur5minuten":"11:00","datum":"2018-12-09","tegenrichting":0,"hoofdrichting":0,"totaal":0,"locatie":"Bataviabrug"},{"uur5minuten":"12:00","datum":"2018-12-09","tegenrichting":0,"hoofdrichting":0,"totaal":0,"locatie":"Bataviabrug"},{"uur5minuten":"13:00","datum":"2018-12-09","tegenrichting":0,"hoofdrichting":0,"totaal":0,"locatie":"Bataviabrug"},{"uur5minuten":"14:00","datum":"2018-12-09","tegenrichting":0,"hoofdrichting":0,"totaal":0,"locatie":"Bataviabrug"},{"uur5minuten":"15:00","datum":"2018-12-09","tegenrichting":0,"hoofdrichting":0,"totaal":0,"locatie":"Bataviabrug"},{"uur5minuten":"16:00","datum":"2018-12-09","tegenrichting":0,"hoofdrichting":0,"totaal":0,"locatie":"Bataviabrug"},{"uur5minuten":"17:00","datum":"2018-12-09","tegenrichting":0,"hoofdrichting":0,"totaal":0,"locatie":"Bataviabrug"},{"uur5minuten":"18:00","datum":"2018-12-09","tegenrichting":0,"hoofdrichting":0,"totaal":0,"locatie":"Bataviabrug"},{"uur5minuten":"19:00","datum":"2018-12-09","tegenrichting":0,"hoofdrichting":0,"totaal":0,"locatie":"Bataviabrug"},{"uur5minuten":"20:00","datum":"2018-12-09","tegenrichting":0,"hoofdrichting":0,"totaal":0,"locatie":"Bataviabrug"},{"uur5minuten":"21:00","datum":"2018-12-09","tegenrichting":0,"hoofdrichting":0,"totaal":0,"locatie":"Bataviabrug"},{"uur5minuten":"22:00","datum":"2018-12-09","tegenrichting":0,"hoofdrichting":0,"totaal":0,"locatie":"Bataviabrug"},{"uur5minuten":"23:00","datum":"2018-12-09","tegenrichting":0,"hoofdrichting":0,"totaal":0,"locatie":"Bataviabrug"},{"uur5minuten":"0:00","datum":"2018-12-10","tegenrichting":0,"hoofdrichting":0,"totaal":0,"locatie":"Bataviabrug"},{"uur5minuten":"1:00","datum":"2018-12-10","tegenrichting":0,"hoofdrichting":0,"totaal":0,"locatie":"Bataviabrug"},{"uur5minuten":"2:00","datum":"2018-12-10","tegenrichting":0,"hoofdrichting":0,"totaal":0,"locatie":"Bataviabrug"},{"uur5minuten":"3:00","datum":"2018-12-10","tegenrichting":0,"hoofdrichting":0,"totaal":0,"locatie":"Bataviabrug"},{"uur5minuten":"4:00","datum":"2018-12-10","tegenrichting":0,"hoofdrichting":0,"totaal":0,"locatie":"Bataviabrug"},{"uur5minuten":"5:00","datum":"2018-12-10","tegenrichting":0,"hoofdrichting":0,"totaal":0,"locatie":"Bataviabrug"},{"uur5minuten":"6:00","datum":"2018-12-10","tegenrichting":0,"hoofdrichting":0,"totaal":0,"locatie":"Bataviabrug"},{"uur5minuten":"7:00","datum":"2018-12-10","tegenrichting":0,"hoofdrichting":0,"totaal":0,"locatie":"Bataviabrug"},{"uur5minuten":"8:00","datum":"2018-12-10","tegenrichting":0,"hoofdrichting":0,"totaal":0,"locatie":"Bataviabrug"},{"uur5minuten":"9:00","datum":"2018-12-10","tegenrichting":0,"hoofdrichting":0,"totaal":0,"locatie":"Bataviabrug"},{"uur5minuten":"10:00","datum":"2018-12-10","tegenrichting":0,"hoofdrichting":0,"totaal":0,"locatie":"Bataviabrug"},{"uur5minuten":"11:00","datum":"2018-12-10","tegenrichting":0,"hoofdrichting":0,"totaal":0,"locatie":"Bataviabrug"},{"uur5minuten":"12:00","datum":"2018-12-10","tegenrichting":0,"hoofdrichting":0,"totaal":0,"locatie":"Bataviabrug"},{"uur5minuten":"13:00","datum":"2018-12-10","tegenrichting":0,"hoofdrichting":0,"totaal":0,"locatie":"Bataviabrug"},{"uur5minuten":"14:00","datum":"2018-12-10","tegenrichting":0,"hoofdrichting":0,"totaal":0,"locatie":"Bataviabrug"},{"uur5minuten":"15:00","datum":"2018-12-10","tegenrichting":0,"hoofdrichting":0,"totaal":0,"locatie":"Bataviabrug"},{"uur5minuten":"16:00","datum":"2018-12-10","tegenrichting":0,"hoofdrichting":0,"totaal":0,"locatie":"Bataviabrug"},{"uur5minuten":"17:00","datum":"2018-12-10","tegenrichting":0,"hoofdrichting":0,"totaal":0,"locatie":"Bataviabrug"},{"uur5minuten":"18:00","datum":"2018-12-10","tegenrichting":0,"hoofdrichting":0,"totaal":0,"locatie":"Bataviabrug"},{"uur5minuten":"19:00","datum":"2018-12-10","tegenrichting":0,"hoofdrichting":0,"totaal":0,"locatie":"Bataviabrug"},{"uur5minuten":"20:00","datum":"2018-12-10","tegenrichting":0,"hoofdrichting":0,"totaal":0,"locatie":"Bataviabrug"},{"uur5minuten":"21:00","datum":"2018-12-10","tegenrichting":0,"hoofdrichting":0,"totaal":0,"locatie":"Bataviabrug"},{"uur5minuten":"22:00","datum":"2018-12-10","tegenrichting":0,"hoofdrichting":0,"totaal":0,"locatie":"Bataviabrug"},{"uur5minuten":"23:00","datum":"2018-12-10","tegenrichting":0,"hoofdrichting":0,"totaal":0,"locatie":"Bataviabrug"},{"uur5minuten":"0:00","datum":"2018-12-11","tegenrichting":0,"hoofdrichting":0,"totaal":0,"locatie":"Bataviabrug"},{"uur5minuten":"1:00","datum":"2018-12-11","tegenrichting":0,"hoofdrichting":0,"totaal":0,"locatie":"Bataviabrug"},{"uur5minuten":"2:00","datum":"2018-12-11","tegenrichting":0,"hoofdrichting":0,"totaal":0,"locatie":"Bataviabrug"},{"uur5minuten":"3:00","datum":"2018-12-11","tegenrichting":0,"hoofdrichting":0,"totaal":0,"locatie":"Bataviabrug"},{"uur5minuten":"4:00","datum":"2018-12-11","tegenrichting":0,"hoofdrichting":0,"totaal":0,"locatie":"Bataviabrug"},{"uur5minuten":"5:00","datum":"2018-12-11","tegenrichting":0,"hoofdrichting":0,"totaal":0,"locatie":"Bataviabrug"},{"uur5minuten":"6:00","datum":"2018-12-11","tegenrichting":0,"hoofdrichting":0,"totaal":0,"locatie":"Bataviabrug"},{"uur5minuten":"7:00","datum":"2018-12-11","tegenrichting":0,"hoofdrichting":0,"totaal":0,"locatie":"Bataviabrug"},{"uur5minuten":"8:00","datum":"2018-12-11","tegenrichting":0,"hoofdrichting":0,"totaal":0,"locatie":"Bataviabrug"},{"uur5minuten":"9:00","datum":"2018-12-11","tegenrichting":0,"hoofdrichting":0,"totaal":0,"locatie":"Bataviabrug"},{"uur5minuten":"10:00","datum":"2018-12-11","tegenrichting":0,"hoofdrichting":0,"totaal":0,"locatie":"Bataviabrug"},{"uur5minuten":"11:00","datum":"2018-12-11","tegenrichting":0,"hoofdrichting":0,"totaal":0,"locatie":"Bataviabrug"},{"uur5minuten":"12:00","datum":"2018-12-11","tegenrichting":0,"hoofdrichting":0,"totaal":0,"locatie":"Bataviabrug"},{"uur5minuten":"13:00","datum":"2018-12-11","tegenrichting":0,"hoofdrichting":0,"totaal":0,"locatie":"Bataviabrug"},{"uur5minuten":"14:00","datum":"2018-12-11","tegenrichting":0,"hoofdrichting":0,"totaal":0,"locatie":"Bataviabrug"},{"uur5minuten":"15:00","datum":"2018-12-11","tegenrichting":0,"hoofdrichting":0,"totaal":0,"locatie":"Bataviabrug"},{"uur5minuten":"16:00","datum":"2018-12-11","tegenrichting":0,"hoofdrichting":0,"totaal":0,"locatie":"Bataviabrug"},{"uur5minuten":"17:00","datum":"2018-12-11","tegenrichting":0,"hoofdrichting":0,"totaal":0,"locatie":"Bataviabrug"},{"uur5minuten":"18:00","datum":"2018-12-11","tegenrichting":0,"hoofdrichting":0,"totaal":0,"locatie":"Bataviabrug"},{"uur5minuten":"19:00","datum":"2018-12-11","tegenrichting":0,"hoofdrichting":0,"totaal":0,"locatie":"Bataviabrug"},{"uur5minuten":"20:00","datum":"2018-12-11","tegenrichting":0,"hoofdrichting":0,"totaal":0,"locatie":"Bataviabrug"},{"uur5minuten":"21:00","datum":"2018-12-11","tegenrichting":0,"hoofdrichting":0,"totaal":0,"locatie":"Bataviabrug"},{"uur5minuten":"22:00","datum":"2018-12-11","tegenrichting":0,"hoofdrichting":0,"totaal":0,"locatie":"Bataviabrug"},{"uur5minuten":"23:00","datum":"2018-12-11","tegenrichting":0,"hoofdrichting":0,"totaal":0,"locatie":"Bataviabrug"},{"uur5minuten":"0:00","datum":"2018-12-12","tegenrichting":0,"hoofdrichting":0,"totaal":0,"locatie":"Bataviabrug"},{"uur5minuten":"1:00","datum":"2018-12-12","tegenrichting":0,"hoofdrichting":0,"totaal":0,"locatie":"Bataviabrug"},{"uur5minuten":"2:00","datum":"2018-12-12","tegenrichting":0,"hoofdrichting":0,"totaal":0,"locatie":"Bataviabrug"},{"uur5minuten":"3:00","datum":"2018-12-12","tegenrichting":0,"hoofdrichting":0,"totaal":0,"locatie":"Bataviabrug"},{"uur5minuten":"4:00","datum":"2018-12-12","tegenrichting":0,"hoofdrichting":0,"totaal":0,"locatie":"Bataviabrug"},{"uur5minuten":"5:00","datum":"2018-12-12","tegenrichting":0,"hoofdrichting":0,"totaal":0,"locatie":"Bataviabrug"},{"uur5minuten":"6:00","datum":"2018-12-12","tegenrichting":0,"hoofdrichting":0,"totaal":0,"locatie":"Bataviabrug"},{"uur5minuten":"7:00","datum":"2018-12-12","tegenrichting":0,"hoofdrichting":0,"totaal":0,"locatie":"Bataviabrug"},{"uur5minuten":"8:00","datum":"2018-12-12","tegenrichting":0,"hoofdrichting":0,"totaal":0,"locatie":"Bataviabrug"},{"uur5minuten":"9:00","datum":"2018-12-12","tegenrichting":0,"hoofdrichting":0,"totaal":0,"locatie":"Bataviabrug"},{"uur5minuten":"10:00","datum":"2018-12-12","tegenrichting":0,"hoofdrichting":0,"totaal":0,"locatie":"Bataviabrug"},{"uur5minuten":"11:00","datum":"2018-12-12","tegenrichting":0,"hoofdrichting":0,"totaal":0,"locatie":"Bataviabrug"},{"uur5minuten":"12:00","datum":"2018-12-12","tegenrichting":0,"hoofdrichting":0,"totaal":0,"locatie":"Bataviabrug"},{"uur5minuten":"13:00","datum":"2018-12-12","tegenrichting":0,"hoofdrichting":0,"totaal":0,"locatie":"Bataviabrug"},{"uur5minuten":"14:00","datum":"2018-12-12","tegenrichting":0,"hoofdrichting":0,"totaal":0,"locatie":"Bataviabrug"},{"uur5minuten":"15:00","datum":"2018-12-12","tegenrichting":0,"hoofdrichting":0,"totaal":0,"locatie":"Bataviabrug"},{"uur5minuten":"16:00","datum":"2018-12-12","tegenrichting":0,"hoofdrichting":0,"totaal":0,"locatie":"Bataviabrug"},{"uur5minuten":"17:00","datum":"2018-12-12","tegenrichting":0,"hoofdrichting":0,"totaal":0,"locatie":"Bataviabrug"},{"uur5minuten":"18:00","datum":"2018-12-12","tegenrichting":0,"hoofdrichting":0,"totaal":0,"locatie":"Bataviabrug"},{"uur5minuten":"19:00","datum":"2018-12-12","tegenrichting":0,"hoofdrichting":0,"totaal":0,"locatie":"Bataviabrug"},{"uur5minuten":"20:00","datum":"2018-12-12","tegenrichting":0,"hoofdrichting":0,"totaal":0,"locatie":"Bataviabrug"},{"uur5minuten":"21:00","datum":"2018-12-12","tegenrichting":0,"hoofdrichting":0,"totaal":0,"locatie":"Bataviabrug"},{"uur5minuten":"22:00","datum":"2018-12-12","tegenrichting":0,"hoofdrichting":0,"totaal":0,"locatie":"Bataviabrug"},{"uur5minuten":"23:00","datum":"2018-12-12","tegenrichting":0,"hoofdrichting":0,"totaal":0,"locatie":"Bataviabrug"},{"uur5minuten":"0:00","datum":"2018-12-13","tegenrichting":0,"hoofdrichting":0,"totaal":0,"locatie":"Bataviabrug"},{"uur5minuten":"1:00","datum":"2018-12-13","tegenrichting":0,"hoofdrichting":0,"totaal":0,"locatie":"Bataviabrug"},{"uur5minuten":"2:00","datum":"2018-12-13","tegenrichting":0,"hoofdrichting":0,"totaal":0,"locatie":"Bataviabrug"},{"uur5minuten":"3:00","datum":"2018-12-13","tegenrichting":0,"hoofdrichting":0,"totaal":0,"locatie":"Bataviabrug"},{"uur5minuten":"4:00","datum":"2018-12-13","tegenrichting":0,"hoofdrichting":0,"totaal":0,"locatie":"Bataviabrug"},{"uur5minuten":"5:00","datum":"2018-12-13","tegenrichting":0,"hoofdrichting":0,"totaal":0,"locatie":"Bataviabrug"},{"uur5minuten":"6:00","datum":"2018-12-13","tegenrichting":0,"hoofdrichting":0,"totaal":0,"locatie":"Bataviabrug"},{"uur5minuten":"7:00","datum":"2018-12-13","tegenrichting":0,"hoofdrichting":0,"totaal":0,"locatie":"Bataviabrug"},{"uur5minuten":"8:00","datum":"2018-12-13","tegenrichting":0,"hoofdrichting":0,"totaal":0,"locatie":"Bataviabrug"},{"uur5minuten":"9:00","datum":"2018-12-13","tegenrichting":0,"hoofdrichting":0,"totaal":0,"locatie":"Bataviabrug"},{"uur5minuten":"10:00","datum":"2018-12-13","tegenrichting":0,"hoofdrichting":0,"totaal":0,"locatie":"Bataviabrug"},{"uur5minuten":"11:00","datum":"2018-12-13","tegenrichting":0,"hoofdrichting":0,"totaal":0,"locatie":"Bataviabrug"},{"uur5minuten":"12:00","datum":"2018-12-13","tegenrichting":0,"hoofdrichting":0,"totaal":0,"locatie":"Bataviabrug"},{"uur5minuten":"13:00","datum":"2018-12-13","tegenrichting":0,"hoofdrichting":0,"totaal":0,"locatie":"Bataviabrug"},{"uur5minuten":"14:00","datum":"2018-12-13","tegenrichting":0,"hoofdrichting":0,"totaal":0,"locatie":"Bataviabrug"},{"uur5minuten":"15:00","datum":"2018-12-13","tegenrichting":0,"hoofdrichting":0,"totaal":0,"locatie":"Bataviabrug"},{"uur5minuten":"16:00","datum":"2018-12-13","tegenrichting":0,"hoofdrichting":0,"totaal":0,"locatie":"Bataviabrug"},{"uur5minuten":"17:00","datum":"2018-12-13","tegenrichting":0,"hoofdrichting":0,"totaal":0,"locatie":"Bataviabrug"},{"uur5minuten":"18:00","datum":"2018-12-13","tegenrichting":0,"hoofdrichting":0,"totaal":0,"locatie":"Bataviabrug"},{"uur5minuten":"19:00","datum":"2018-12-13","tegenrichting":0,"hoofdrichting":0,"totaal":0,"locatie":"Bataviabrug"},{"uur5minuten":"20:00","datum":"2018-12-13","tegenrichting":0,"hoofdrichting":0,"totaal":0,"locatie":"Bataviabrug"},{"uur5minuten":"21:00","datum":"2018-12-13","tegenrichting":0,"hoofdrichting":0,"totaal":0,"locatie":"Bataviabrug"},{"uur5minuten":"22:00","datum":"2018-12-13","tegenrichting":0,"hoofdrichting":0,"totaal":0,"locatie":"Bataviabrug"},{"uur5minuten":"23:00","datum":"2018-12-13","tegenrichting":0,"hoofdrichting":0,"totaal":0,"locatie":"Bataviabrug"},{"uur5minuten":"0:00","datum":"2018-12-14","tegenrichting":2,"hoofdrichting":5,"totaal":7,"locatie":"Bataviabrug"},{"uur5minuten":"1:00","datum":"2018-12-14","tegenrichting":1,"hoofdrichting":1,"totaal":2,"locatie":"Bataviabrug"},{"uur5minuten":"2:00","datum":"2018-12-14","tegenrichting":1,"hoofdrichting":1,"totaal":2,"locatie":"Bataviabrug"},{"uur5minuten":"3:00","datum":"2018-12-14","tegenrichting":1,"hoofdrichting":0,"totaal":1,"locatie":"Bataviabrug"},{"uur5minuten":"4:00","datum":"2018-12-14","tegenrichting":1,"hoofdrichting":0,"totaal":1,"locatie":"Bataviabrug"},{"uur5minuten":"5:00","datum":"2018-12-14","tegenrichting":3,"hoofdrichting":3,"totaal":6,"locatie":"Bataviabrug"},{"uur5minuten":"6:00","datum":"2018-12-14","tegenrichting":12,"hoofdrichting":10,"totaal":22,"locatie":"Bataviabrug"},{"uur5minuten":"7:00","datum":"2018-12-14","tegenrichting":17,"hoofdrichting":28,"totaal":45,"locatie":"Bataviabrug"},{"uur5minuten":"8:00","datum":"2018-12-14","tegenrichting":70,"hoofdrichting":30,"totaal":100,"locatie":"Bataviabrug"},{"uur5minuten":"9:00","datum":"2018-12-14","tegenrichting":40,"hoofdrichting":22,"totaal":62,"locatie":"Bataviabrug"},{"uur5minuten":"10:00","datum":"2018-12-14","tegenrichting":13,"hoofdrichting":10,"totaal":23,"locatie":"Bataviabrug"},{"uur5minuten":"11:00","datum":"2018-12-14","tegenrichting":24,"hoofdrichting":16,"totaal":40,"locatie":"Bataviabrug"},{"uur5minuten":"12:00","datum":"2018-12-14","tegenrichting":35,"hoofdrichting":33,"totaal":68,"locatie":"Bataviabrug"},{"uur5minuten":"13:00","datum":"2018-12-14","tegenrichting":37,"hoofdrichting":26,"totaal":63,"locatie":"Bataviabrug"},{"uur5minuten":"14:00","datum":"2018-12-14","tegenrichting":23,"hoofdrichting":29,"totaal":52,"locatie":"Bataviabrug"},{"uur5minuten":"15:00","datum":"2018-12-14","tegenrichting":23,"hoofdrichting":39,"totaal":62,"locatie":"Bataviabrug"},{"uur5minuten":"16:00","datum":"2018-12-14","tegenrichting":31,"hoofdrichting":48,"totaal":79,"locatie":"Bataviabrug"},{"uur5minuten":"17:00","datum":"2018-12-14","tegenrichting":45,"hoofdrichting":58,"totaal":103,"locatie":"Bataviabrug"},{"uur5minuten":"18:00","datum":"2018-12-14","tegenrichting":33,"hoofdrichting":34,"totaal":67,"locatie":"Bataviabrug"},{"uur5minuten":"19:00","datum":"2018-12-14","tegenrichting":36,"hoofdrichting":18,"totaal":54,"locatie":"Bataviabrug"},{"uur5minuten":"20:00","datum":"2018-12-14","tegenrichting":25,"hoofdrichting":14,"totaal":39,"locatie":"Bataviabrug"},{"uur5minuten":"21:00","datum":"2018-12-14","tegenrichting":6,"hoofdrichting":12,"totaal":18,"locatie":"Bataviabrug"},{"uur5minuten":"22:00","datum":"2018-12-14","tegenrichting":12,"hoofdrichting":21,"totaal":33,"locatie":"Bataviabrug"},{"uur5minuten":"23:00","datum":"2018-12-14","tegenrichting":2,"hoofdrichting":9,"totaal":11,"locatie":"Bataviabrug"},{"uur5minuten":"0:00","datum":"2018-12-15","tegenrichting":7,"hoofdrichting":15,"totaal":22,"locatie":"Bataviabrug"},{"uur5minuten":"1:00","datum":"2018-12-15","tegenrichting":7,"hoofdrichting":10,"totaal":17,"locatie":"Bataviabrug"},{"uur5minuten":"2:00","datum":"2018-12-15","tegenrichting":2,"hoofdrichting":9,"totaal":11,"locatie":"Bataviabrug"},{"uur5minuten":"3:00","datum":"2018-12-15","tegenrichting":1,"hoofdrichting":8,"totaal":9,"locatie":"Bataviabrug"},{"uur5minuten":"4:00","datum":"2018-12-15","tegenrichting":4,"hoofdrichting":10,"totaal":14,"locatie":"Bataviabrug"},{"uur5minuten":"5:00","datum":"2018-12-15","tegenrichting":0,"hoofdrichting":1,"totaal":1,"locatie":"Bataviabrug"},{"uur5minuten":"6:00","datum":"2018-12-15","tegenrichting":0,"hoofdrichting":4,"totaal":4,"locatie":"Bataviabrug"},{"uur5minuten":"7:00","datum":"2018-12-15","tegenrichting":4,"hoofdrichting":2,"totaal":6,"locatie":"Bataviabrug"},{"uur5minuten":"8:00","datum":"2018-12-15","tegenrichting":5,"hoofdrichting":8,"totaal":13,"locatie":"Bataviabrug"},{"uur5minuten":"9:00","datum":"2018-12-15","tegenrichting":16,"hoofdrichting":14,"totaal":30,"locatie":"Bataviabrug"},{"uur5minuten":"10:00","datum":"2018-12-15","tegenrichting":27,"hoofdrichting":11,"totaal":38,"locatie":"Bataviabrug"},{"uur5minuten":"11:00","datum":"2018-12-15","tegenrichting":15,"hoofdrichting":23,"totaal":38,"locatie":"Bataviabrug"},{"uur5minuten":"12:00","datum":"2018-12-15","tegenrichting":27,"hoofdrichting":38,"totaal":65,"locatie":"Bataviabrug"},{"uur5minuten":"13:00","datum":"2018-12-15","tegenrichting":21,"hoofdrichting":26,"totaal":47,"locatie":"Bataviabrug"},{"uur5minuten":"14:00","datum":"2018-12-15","tegenrichting":30,"hoofdrichting":26,"totaal":56,"locatie":"Bataviabrug"},{"uur5minuten":"15:00","datum":"2018-12-15","tegenrichting":20,"hoofdrichting":25,"totaal":45,"locatie":"Bataviabrug"},{"uur5minuten":"16:00","datum":"2018-12-15","tegenrichting":27,"hoofdrichting":23,"totaal":50,"locatie":"Bataviabrug"},{"uur5minuten":"17:00","datum":"2018-12-15","tegenrichting":15,"hoofdrichting":39,"totaal":54,"locatie":"Bataviabrug"},{"uur5minuten":"18:00","datum":"2018-12-15","tegenrichting":17,"hoofdrichting":16,"totaal":33,"locatie":"Bataviabrug"},{"uur5minuten":"19:00","datum":"2018-12-15","tegenrichting":28,"hoofdrichting":13,"totaal":41,"locatie":"Bataviabrug"},{"uur5minuten":"20:00","datum":"2018-12-15","tegenrichting":11,"hoofdrichting":4,"totaal":15,"locatie":"Bataviabrug"},{"uur5minuten":"21:00","datum":"2018-12-15","tegenrichting":4,"hoofdrichting":6,"totaal":10,"locatie":"Bataviabrug"},{"uur5minuten":"22:00","datum":"2018-12-15","tegenrichting":5,"hoofdrichting":15,"totaal":20,"locatie":"Bataviabrug"},{"uur5minuten":"23:00","datum":"2018-12-15","tegenrichting":3,"hoofdrichting":12,"totaal":15,"locatie":"Bataviabrug"},{"uur5minuten":"0:00","datum":"2018-12-16","tegenrichting":4,"hoofdrichting":18,"totaal":22,"locatie":"Bataviabrug"},{"uur5minuten":"1:00","datum":"2018-12-16","tegenrichting":1,"hoofdrichting":15,"totaal":16,"locatie":"Bataviabrug"},{"uur5minuten":"2:00","datum":"2018-12-16","tegenrichting":2,"hoofdrichting":4,"totaal":6,"locatie":"Bataviabrug"},{"uur5minuten":"3:00","datum":"2018-12-16","tegenrichting":0,"hoofdrichting":3,"totaal":3,"locatie":"Bataviabrug"},{"uur5minuten":"4:00","datum":"2018-12-16","tegenrichting":1,"hoofdrichting":1,"totaal":2,"locatie":"Bataviabrug"},{"uur5minuten":"5:00","datum":"2018-12-16","tegenrichting":0,"hoofdrichting":1,"totaal":1,"locatie":"Bataviabrug"},{"uur5minuten":"6:00","datum":"2018-12-16","tegenrichting":1,"hoofdrichting":2,"totaal":3,"locatie":"Bataviabrug"},{"uur5minuten":"7:00","datum":"2018-12-16","tegenrichting":0,"hoofdrichting":1,"totaal":1,"locatie":"Bataviabrug"},{"uur5minuten":"8:00","datum":"2018-12-16","tegenrichting":7,"hoofdrichting":8,"totaal":15,"locatie":"Bataviabrug"},{"uur5minuten":"9:00","datum":"2018-12-16","tegenrichting":12,"hoofdrichting":5,"totaal":17,"locatie":"Bataviabrug"},{"uur5minuten":"10:00","datum":"2018-12-16","tegenrichting":12,"hoofdrichting":14,"totaal":26,"locatie":"Bataviabrug"},{"uur5minuten":"11:00","datum":"2018-12-16","tegenrichting":20,"hoofdrichting":14,"totaal":34,"locatie":"Bataviabrug"},{"uur5minuten":"12:00","datum":"2018-12-16","tegenrichting":17,"hoofdrichting":18,"totaal":35,"locatie":"Bataviabrug"},{"uur5minuten":"13:00","datum":"2018-12-16","tegenrichting":12,"hoofdrichting":14,"totaal":26,"locatie":"Bataviabrug"},{"uur5minuten":"14:00","datum":"2018-12-16","tegenrichting":19,"hoofdrichting":17,"totaal":36,"locatie":"Bataviabrug"},{"uur5minuten":"15:00","datum":"2018-12-16","tegenrichting":10,"hoofdrichting":25,"totaal":35,"locatie":"Bataviabrug"},{"uur5minuten":"16:00","datum":"2018-12-16","tegenrichting":20,"hoofdrichting":22,"totaal":42,"locatie":"Bataviabrug"},{"uur5minuten":"17:00","datum":"2018-12-16","tegenrichting":9,"hoofdrichting":20,"totaal":29,"locatie":"Bataviabrug"},{"uur5minuten":"18:00","datum":"2018-12-16","tegenrichting":18,"hoofdrichting":11,"totaal":29,"locatie":"Bataviabrug"},{"uur5minuten":"19:00","datum":"2018-12-16","tegenrichting":8,"hoofdrichting":13,"totaal":21,"locatie":"Bataviabrug"},{"uur5minuten":"20:00","datum":"2018-12-16","tegenrichting":9,"hoofdrichting":4,"totaal":13,"locatie":"Bataviabrug"},{"uur5minuten":"21:00","datum":"2018-12-16","tegenrichting":6,"hoofdrichting":7,"totaal":13,"locatie":"Bataviabrug"},{"uur5minuten":"22:00","datum":"2018-12-16","tegenrichting":6,"hoofdrichting":2,"totaal":8,"locatie":"Bataviabrug"},{"uur5minuten":"23:00","datum":"2018-12-16","tegenrichting":4,"hoofdrichting":3,"totaal":7,"locatie":"Bataviabrug"},{"uur5minuten":"0:00","datum":"2018-12-17","tegenrichting":1,"hoofdrichting":1,"totaal":2,"locatie":"Bataviabrug"},{"uur5minuten":"1:00","datum":"2018-12-17","tegenrichting":2,"hoofdrichting":0,"totaal":2,"locatie":"Bataviabrug"},{"uur5minuten":"2:00","datum":"2018-12-17","tegenrichting":0,"hoofdrichting":1,"totaal":1,"locatie":"Bataviabrug"},{"uur5minuten":"3:00","datum":"2018-12-17","tegenrichting":0,"hoofdrichting":0,"totaal":0,"locatie":"Bataviabrug"},{"uur5minuten":"4:00","datum":"2018-12-17","tegenrichting":0,"hoofdrichting":5,"totaal":5,"locatie":"Bataviabrug"},{"uur5minuten":"5:00","datum":"2018-12-17","tegenrichting":5,"hoofdrichting":4,"totaal":9,"locatie":"Bataviabrug"},{"uur5minuten":"6:00","datum":"2018-12-17","tegenrichting":6,"hoofdrichting":6,"totaal":12,"locatie":"Bataviabrug"},{"uur5minuten":"7:00","datum":"2018-12-17","tegenrichting":42,"hoofdrichting":20,"totaal":62,"locatie":"Bataviabrug"},{"uur5minuten":"8:00","datum":"2018-12-17","tegenrichting":104,"hoofdrichting":32,"totaal":136,"locatie":"Bataviabrug"},{"uur5minuten":"9:00","datum":"2018-12-17","tegenrichting":37,"hoofdrichting":9,"totaal":46,"locatie":"Bataviabrug"},{"uur5minuten":"10:00","datum":"2018-12-17","tegenrichting":19,"hoofdrichting":19,"totaal":38,"locatie":"Bataviabrug"},{"uur5minuten":"11:00","datum":"2018-12-17","tegenrichting":23,"hoofdrichting":25,"totaal":48,"locatie":"Bataviabrug"},{"uur5minuten":"12:00","datum":"2018-12-17","tegenrichting":24,"hoofdrichting":19,"totaal":43,"locatie":"Bataviabrug"},{"uur5minuten":"13:00","datum":"2018-12-17","tegenrichting":26,"hoofdrichting":35,"totaal":61,"locatie":"Bataviabrug"},{"uur5minuten":"14:00","datum":"2018-12-17","tegenrichting":36,"hoofdrichting":43,"totaal":79,"locatie":"Bataviabrug"},{"uur5minuten":"15:00","datum":"2018-12-17","tegenrichting":24,"hoofdrichting":40,"totaal":64,"locatie":"Bataviabrug"},{"uur5minuten":"16:00","datum":"2018-12-17","tegenrichting":41,"hoofdrichting":86,"totaal":127,"locatie":"Bataviabrug"},{"uur5minuten":"17:00","datum":"2018-12-17","tegenrichting":38,"hoofdrichting":72,"totaal":110,"locatie":"Bataviabrug"},{"uur5minuten":"18:00","datum":"2018-12-17","tegenrichting":34,"hoofdrichting":38,"totaal":72,"locatie":"Bataviabrug"},{"uur5minuten":"19:00","datum":"2018-12-17","tegenrichting":35,"hoofdrichting":24,"totaal":59,"locatie":"Bataviabrug"},{"uur5minuten":"20:00","datum":"2018-12-17","tegenrichting":12,"hoofdrichting":14,"totaal":26,"locatie":"Bataviabrug"},{"uur5minuten":"21:00","datum":"2018-12-17","tegenrichting":2,"hoofdrichting":15,"totaal":17,"locatie":"Bataviabrug"},{"uur5minuten":"22:00","datum":"2018-12-17","tegenrichting":11,"hoofdrichting":15,"totaal":26,"locatie":"Bataviabrug"},{"uur5minuten":"23:00","datum":"2018-12-17","tegenrichting":1,"hoofdrichting":6,"totaal":7,"locatie":"Bataviabrug"},{"uur5minuten":"0:00","datum":"2018-12-18","tegenrichting":2,"hoofdrichting":5,"totaal":7,"locatie":"Bataviabrug"},{"uur5minuten":"1:00","datum":"2018-12-18","tegenrichting":1,"hoofdrichting":2,"totaal":3,"locatie":"Bataviabrug"},{"uur5minuten":"2:00","datum":"2018-12-18","tegenrichting":0,"hoofdrichting":0,"totaal":0,"locatie":"Bataviabrug"},{"uur5minuten":"3:00","datum":"2018-12-18","tegenrichting":0,"hoofdrichting":0,"totaal":0,"locatie":"Bataviabrug"},{"uur5minuten":"4:00","datum":"2018-12-18","tegenrichting":0,"hoofdrichting":4,"totaal":4,"locatie":"Bataviabrug"},{"uur5minuten":"5:00","datum":"2018-12-18","tegenrichting":0,"hoofdrichting":0,"totaal":0,"locatie":"Bataviabrug"},{"uur5minuten":"6:00","datum":"2018-12-18","tegenrichting":13,"hoofdrichting":8,"totaal":21,"locatie":"Bataviabrug"},{"uur5minuten":"7:00","datum":"2018-12-18","tegenrichting":49,"hoofdrichting":28,"totaal":77,"locatie":"Bataviabrug"},{"uur5minuten":"8:00","datum":"2018-12-18","tegenrichting":93,"hoofdrichting":33,"totaal":126,"locatie":"Bataviabrug"},{"uur5minuten":"9:00","datum":"2018-12-18","tegenrichting":52,"hoofdrichting":24,"totaal":76,"locatie":"Bataviabrug"},{"uur5minuten":"10:00","datum":"2018-12-18","tegenrichting":29,"hoofdrichting":18,"totaal":47,"locatie":"Bataviabrug"},{"uur5minuten":"11:00","datum":"2018-12-18","tegenrichting":26,"hoofdrichting":14,"totaal":40,"locatie":"Bataviabrug"},{"uur5minuten":"12:00","datum":"2018-12-18","tegenrichting":20,"hoofdrichting":32,"totaal":52,"locatie":"Bataviabrug"},{"uur5minuten":"13:00","datum":"2018-12-18","tegenrichting":33,"hoofdrichting":33,"totaal":66,"locatie":"Bataviabrug"},{"uur5minuten":"14:00","datum":"2018-12-18","tegenrichting":22,"hoofdrichting":16,"totaal":38,"locatie":"Bataviabrug"},{"uur5minuten":"15:00","datum":"2018-12-18","tegenrichting":24,"hoofdrichting":21,"totaal":45,"locatie":"Bataviabrug"},{"uur5minuten":"16:00","datum":"2018-12-18","tegenrichting":45,"hoofdrichting":63,"totaal":108,"locatie":"Bataviabrug"},{"uur5minuten":"17:00","datum":"2018-12-18","tegenrichting":50,"hoofdrichting":85,"totaal":135,"locatie":"Bataviabrug"},{"uur5minuten":"18:00","datum":"2018-12-18","tegenrichting":24,"hoofdrichting":53,"totaal":77,"locatie":"Bataviabrug"},{"uur5minuten":"19:00","datum":"2018-12-18","tegenrichting":23,"hoofdrichting":28,"totaal":51,"locatie":"Bataviabrug"},{"uur5minuten":"20:00","datum":"2018-12-18","tegenrichting":22,"hoofdrichting":20,"totaal":42,"locatie":"Bataviabrug"},{"uur5minuten":"21:00","datum":"2018-12-18","tegenrichting":7,"hoofdrichting":22,"totaal":29,"locatie":"Bataviabrug"},{"uur5minuten":"22:00","datum":"2018-12-18","tegenrichting":7,"hoofdrichting":19,"totaal":26,"locatie":"Bataviabrug"},{"uur5minuten":"23:00","datum":"2018-12-18","tegenrichting":3,"hoofdrichting":6,"totaal":9,"locatie":"Bataviabrug"},{"uur5minuten":"0:00","datum":"2018-12-19","tegenrichting":2,"hoofdrichting":0,"totaal":2,"locatie":"Bataviabrug"},{"uur5minuten":"1:00","datum":"2018-12-19","tegenrichting":2,"hoofdrichting":1,"totaal":3,"locatie":"Bataviabrug"},{"uur5minuten":"2:00","datum":"2018-12-19","tegenrichting":0,"hoofdrichting":2,"totaal":2,"locatie":"Bataviabrug"},{"uur5minuten":"3:00","datum":"2018-12-19","tegenrichting":0,"hoofdrichting":0,"totaal":0,"locatie":"Bataviabrug"},{"uur5minuten":"4:00","datum":"2018-12-19","tegenrichting":0,"hoofdrichting":4,"totaal":4,"locatie":"Bataviabrug"},{"uur5minuten":"5:00","datum":"2018-12-19","tegenrichting":1,"hoofdrichting":2,"totaal":3,"locatie":"Bataviabrug"},{"uur5minuten":"6:00","datum":"2018-12-19","tegenrichting":8,"hoofdrichting":7,"totaal":15,"locatie":"Bataviabrug"},{"uur5minuten":"7:00","datum":"2018-12-19","tegenrichting":38,"hoofdrichting":21,"totaal":59,"locatie":"Bataviabrug"},{"uur5minuten":"8:00","datum":"2018-12-19","tegenrichting":95,"hoofdrichting":40,"totaal":135,"locatie":"Bataviabrug"},{"uur5minuten":"9:00","datum":"2018-12-19","tegenrichting":46,"hoofdrichting":16,"totaal":62,"locatie":"Bataviabrug"},{"uur5minuten":"10:00","datum":"2018-12-19","tegenrichting":20,"hoofdrichting":25,"totaal":45,"locatie":"Bataviabrug"},{"uur5minuten":"11:00","datum":"2018-12-19","tegenrichting":31,"hoofdrichting":38,"totaal":69,"locatie":"Bataviabrug"},{"uur5minuten":"12:00","datum":"2018-12-19","tegenrichting":36,"hoofdrichting":36,"totaal":72,"locatie":"Bataviabrug"},{"uur5minuten":"13:00","datum":"2018-12-19","tegenrichting":46,"hoofdrichting":31,"totaal":77,"locatie":"Bataviabrug"},{"uur5minuten":"14:00","datum":"2018-12-19","tegenrichting":24,"hoofdrichting":28,"totaal":52,"locatie":"Bataviabrug"},{"uur5minuten":"15:00","datum":"2018-12-19","tegenrichting":29,"hoofdrichting":33,"totaal":62,"locatie":"Bataviabrug"},{"uur5minuten":"16:00","datum":"2018-12-19","tegenrichting":44,"hoofdrichting":51,"totaal":95,"locatie":"Bataviabrug"},{"uur5minuten":"17:00","datum":"2018-12-19","tegenrichting":46,"hoofdrichting":68,"totaal":114,"locatie":"Bataviabrug"},{"uur5minuten":"18:00","datum":"2018-12-19","tegenrichting":33,"hoofdrichting":39,"totaal":72,"locatie":"Bataviabrug"},{"uur5minuten":"19:00","datum":"2018-12-19","tegenrichting":36,"hoofdrichting":26,"totaal":62,"locatie":"Bataviabrug"},{"uur5minuten":"20:00","datum":"2018-12-19","tegenrichting":21,"hoofdrichting":15,"totaal":36,"locatie":"Bataviabrug"},{"uur5minuten":"21:00","datum":"2018-12-19","tegenrichting":14,"hoofdrichting":16,"totaal":30,"locatie":"Bataviabrug"},{"uur5minuten":"22:00","datum":"2018-12-19","tegenrichting":11,"hoofdrichting":38,"totaal":49,"locatie":"Bataviabrug"},{"uur5minuten":"23:00","datum":"2018-12-19","tegenrichting":7,"hoofdrichting":14,"totaal":21,"locatie":"Bataviabrug"},{"uur5minuten":"0:00","datum":"2018-12-20","tegenrichting":2,"hoofdrichting":9,"totaal":11,"locatie":"Bataviabrug"},{"uur5minuten":"1:00","datum":"2018-12-20","tegenrichting":4,"hoofdrichting":6,"totaal":10,"locatie":"Bataviabrug"},{"uur5minuten":"2:00","datum":"2018-12-20","tegenrichting":0,"hoofdrichting":11,"totaal":11,"locatie":"Bataviabrug"},{"uur5minuten":"3:00","datum":"2018-12-20","tegenrichting":1,"hoofdrichting":9,"totaal":10,"locatie":"Bataviabrug"},{"uur5minuten":"4:00","datum":"2018-12-20","tegenrichting":1,"hoofdrichting":9,"totaal":10,"locatie":"Bataviabrug"},{"uur5minuten":"5:00","datum":"2018-12-20","tegenrichting":2,"hoofdrichting":13,"totaal":15,"locatie":"Bataviabrug"},{"uur5minuten":"6:00","datum":"2018-12-20","tegenrichting":8,"hoofdrichting":11,"totaal":19,"locatie":"Bataviabrug"},{"uur5minuten":"7:00","datum":"2018-12-20","tegenrichting":36,"hoofdrichting":18,"totaal":54,"locatie":"Bataviabrug"},{"uur5minuten":"8:00","datum":"2018-12-20","tegenrichting":73,"hoofdrichting":28,"totaal":101,"locatie":"Bataviabrug"},{"uur5minuten":"9:00","datum":"2018-12-20","tegenrichting":57,"hoofdrichting":17,"totaal":74,"locatie":"Bataviabrug"},{"uur5minuten":"10:00","datum":"2018-12-20","tegenrichting":17,"hoofdrichting":17,"totaal":34,"locatie":"Bataviabrug"},{"uur5minuten":"11:00","datum":"2018-12-20","tegenrichting":25,"hoofdrichting":20,"totaal":45,"locatie":"Bataviabrug"},{"uur5minuten":"12:00","datum":"2018-12-20","tegenrichting":22,"hoofdrichting":17,"totaal":39,"locatie":"Bataviabrug"},{"uur5minuten":"13:00","datum":"2018-12-20","tegenrichting":18,"hoofdrichting":20,"totaal":38,"locatie":"Bataviabrug"},{"uur5minuten":"14:00","datum":"2018-12-20","tegenrichting":17,"hoofdrichting":19,"totaal":36,"locatie":"Bataviabrug"},{"uur5minuten":"15:00","datum":"2018-12-20","tegenrichting":28,"hoofdrichting":34,"totaal":62,"locatie":"Bataviabrug"},{"uur5minuten":"16:00","datum":"2018-12-20","tegenrichting":22,"hoofdrichting":55,"totaal":77,"locatie":"Bataviabrug"},{"uur5minuten":"17:00","datum":"2018-12-20","tegenrichting":51,"hoofdrichting":62,"totaal":113,"locatie":"Bataviabrug"},{"uur5minuten":"18:00","datum":"2018-12-20","tegenrichting":34,"hoofdrichting":32,"totaal":66,"locatie":"Bataviabrug"},{"uur5minuten":"19:00","datum":"2018-12-20","tegenrichting":24,"hoofdrichting":15,"totaal":39,"locatie":"Bataviabrug"},{"uur5minuten":"20:00","datum":"2018-12-20","tegenrichting":21,"hoofdrichting":18,"totaal":39,"locatie":"Bataviabrug"},{"uur5minuten":"21:00","datum":"2018-12-20","tegenrichting":4,"hoofdrichting":25,"totaal":29,"locatie":"Bataviabrug"},{"uur5minuten":"22:00","datum":"2018-12-20","tegenrichting":10,"hoofdrichting":17,"totaal":27,"locatie":"Bataviabrug"},{"uur5minuten":"23:00","datum":"2018-12-20","tegenrichting":4,"hoofdrichting":10,"totaal":14,"locatie":"Bataviabrug"},{"uur5minuten":"0:00","datum":"2018-12-21","tegenrichting":6,"hoofdrichting":6,"totaal":12,"locatie":"Bataviabrug"},{"uur5minuten":"1:00","datum":"2018-12-21","tegenrichting":2,"hoofdrichting":4,"totaal":6,"locatie":"Bataviabrug"},{"uur5minuten":"2:00","datum":"2018-12-21","tegenrichting":0,"hoofdrichting":1,"totaal":1,"locatie":"Bataviabrug"},{"uur5minuten":"3:00","datum":"2018-12-21","tegenrichting":0,"hoofdrichting":0,"totaal":0,"locatie":"Bataviabrug"},{"uur5minuten":"4:00","datum":"2018-12-21","tegenrichting":1,"hoofdrichting":0,"totaal":1,"locatie":"Bataviabrug"},{"uur5minuten":"5:00","datum":"2018-12-21","tegenrichting":0,"hoofdrichting":1,"totaal":1,"locatie":"Bataviabrug"},{"uur5minuten":"6:00","datum":"2018-12-21","tegenrichting":7,"hoofdrichting":5,"totaal":12,"locatie":"Bataviabrug"},{"uur5minuten":"7:00","datum":"2018-12-21","tegenrichting":15,"hoofdrichting":18,"totaal":33,"locatie":"Bataviabrug"},{"uur5minuten":"8:00","datum":"2018-12-21","tegenrichting":53,"hoofdrichting":19,"totaal":72,"locatie":"Bataviabrug"},{"uur5minuten":"9:00","datum":"2018-12-21","tegenrichting":36,"hoofdrichting":19,"totaal":55,"locatie":"Bataviabrug"},{"uur5minuten":"10:00","datum":"2018-12-21","tegenrichting":18,"hoofdrichting":8,"totaal":26,"locatie":"Bataviabrug"},{"uur5minuten":"11:00","datum":"2018-12-21","tegenrichting":18,"hoofdrichting":23,"totaal":41,"locatie":"Bataviabrug"},{"uur5minuten":"12:00","datum":"2018-12-21","tegenrichting":33,"hoofdrichting":11,"totaal":44,"locatie":"Bataviabrug"},{"uur5minuten":"13:00","datum":"2018-12-21","tegenrichting":22,"hoofdrichting":26,"totaal":48,"locatie":"Bataviabrug"},{"uur5minuten":"14:00","datum":"2018-12-21","tegenrichting":23,"hoofdrichting":25,"totaal":48,"locatie":"Bataviabrug"},{"uur5minuten":"15:00","datum":"2018-12-21","tegenrichting":25,"hoofdrichting":30,"totaal":55,"locatie":"Bataviabrug"},{"uur5minuten":"16:00","datum":"2018-12-21","tegenrichting":28,"hoofdrichting":28,"totaal":56,"locatie":"Bataviabrug"},{"uur5minuten":"17:00","datum":"2018-12-21","tegenrichting":19,"hoofdrichting":47,"totaal":66,"locatie":"Bataviabrug"},{"uur5minuten":"18:00","datum":"2018-12-21","tegenrichting":22,"hoofdrichting":30,"totaal":52,"locatie":"Bataviabrug"},{"uur5minuten":"19:00","datum":"2018-12-21","tegenrichting":41,"hoofdrichting":22,"totaal":63,"locatie":"Bataviabrug"},{"uur5minuten":"20:00","datum":"2018-12-21","tegenrichting":19,"hoofdrichting":19,"totaal":38,"locatie":"Bataviabrug"},{"uur5minuten":"21:00","datum":"2018-12-21","tegenrichting":6,"hoofdrichting":9,"totaal":15,"locatie":"Bataviabrug"},{"uur5minuten":"22:00","datum":"2018-12-21","tegenrichting":10,"hoofdrichting":27,"totaal":37,"locatie":"Bataviabrug"},{"uur5minuten":"23:00","datum":"2018-12-21","tegenrichting":3,"hoofdrichting":8,"totaal":11,"locatie":"Bataviabrug"},{"uur5minuten":"0:00","datum":"2018-12-22","tegenrichting":6,"hoofdrichting":16,"totaal":22,"locatie":"Bataviabrug"},{"uur5minuten":"1:00","datum":"2018-12-22","tegenrichting":3,"hoofdrichting":8,"totaal":11,"locatie":"Bataviabrug"},{"uur5minuten":"2:00","datum":"2018-12-22","tegenrichting":2,"hoofdrichting":4,"totaal":6,"locatie":"Bataviabrug"},{"uur5minuten":"3:00","datum":"2018-12-22","tegenrichting":2,"hoofdrichting":13,"totaal":15,"locatie":"Bataviabrug"},{"uur5minuten":"4:00","datum":"2018-12-22","tegenrichting":2,"hoofdrichting":7,"totaal":9,"locatie":"Bataviabrug"},{"uur5minuten":"5:00","datum":"2018-12-22","tegenrichting":5,"hoofdrichting":5,"totaal":10,"locatie":"Bataviabrug"},{"uur5minuten":"6:00","datum":"2018-12-22","tegenrichting":1,"hoofdrichting":2,"totaal":3,"locatie":"Bataviabrug"},{"uur5minuten":"7:00","datum":"2018-12-22","tegenrichting":3,"hoofdrichting":0,"totaal":3,"locatie":"Bataviabrug"},{"uur5minuten":"8:00","datum":"2018-12-22","tegenrichting":7,"hoofdrichting":8,"totaal":15,"locatie":"Bataviabrug"},{"uur5minuten":"9:00","datum":"2018-12-22","tegenrichting":10,"hoofdrichting":6,"totaal":16,"locatie":"Bataviabrug"},{"uur5minuten":"10:00","datum":"2018-12-22","tegenrichting":18,"hoofdrichting":12,"totaal":30,"locatie":"Bataviabrug"},{"uur5minuten":"11:00","datum":"2018-12-22","tegenrichting":18,"hoofdrichting":19,"totaal":37,"locatie":"Bataviabrug"},{"uur5minuten":"12:00","datum":"2018-12-22","tegenrichting":15,"hoofdrichting":22,"totaal":37,"locatie":"Bataviabrug"},{"uur5minuten":"13:00","datum":"2018-12-22","tegenrichting":22,"hoofdrichting":23,"totaal":45,"locatie":"Bataviabrug"},{"uur5minuten":"14:00","datum":"2018-12-22","tegenrichting":26,"hoofdrichting":23,"totaal":49,"locatie":"Bataviabrug"},{"uur5minuten":"15:00","datum":"2018-12-22","tegenrichting":29,"hoofdrichting":31,"totaal":60,"locatie":"Bataviabrug"},{"uur5minuten":"16:00","datum":"2018-12-22","tegenrichting":25,"hoofdrichting":26,"totaal":51,"locatie":"Bataviabrug"},{"uur5minuten":"17:00","datum":"2018-12-22","tegenrichting":18,"hoofdrichting":31,"totaal":49,"locatie":"Bataviabrug"},{"uur5minuten":"18:00","datum":"2018-12-22","tegenrichting":18,"hoofdrichting":29,"totaal":47,"locatie":"Bataviabrug"},{"uur5minuten":"19:00","datum":"2018-12-22","tegenrichting":25,"hoofdrichting":21,"totaal":46,"locatie":"Bataviabrug"},{"uur5minuten":"20:00","datum":"2018-12-22","tegenrichting":11,"hoofdrichting":7,"totaal":18,"locatie":"Bataviabrug"},{"uur5minuten":"21:00","datum":"2018-12-22","tegenrichting":6,"hoofdrichting":10,"totaal":16,"locatie":"Bataviabrug"},{"uur5minuten":"22:00","datum":"2018-12-22","tegenrichting":9,"hoofdrichting":8,"totaal":17,"locatie":"Bataviabrug"},{"uur5minuten":"23:00","datum":"2018-12-22","tegenrichting":1,"hoofdrichting":16,"totaal":17,"locatie":"Bataviabrug"},{"uur5minuten":"0:00","datum":"2018-12-23","tegenrichting":7,"hoofdrichting":5,"totaal":12,"locatie":"Bataviabrug"},{"uur5minuten":"1:00","datum":"2018-12-23","tegenrichting":6,"hoofdrichting":13,"totaal":19,"locatie":"Bataviabrug"},{"uur5minuten":"2:00","datum":"2018-12-23","tegenrichting":0,"hoofdrichting":4,"totaal":4,"locatie":"Bataviabrug"},{"uur5minuten":"3:00","datum":"2018-12-23","tegenrichting":1,"hoofdrichting":1,"totaal":2,"locatie":"Bataviabrug"},{"uur5minuten":"4:00","datum":"2018-12-23","tegenrichting":0,"hoofdrichting":2,"totaal":2,"locatie":"Bataviabrug"},{"uur5minuten":"5:00","datum":"2018-12-23","tegenrichting":1,"hoofdrichting":2,"totaal":3,"locatie":"Bataviabrug"},{"uur5minuten":"6:00","datum":"2018-12-23","tegenrichting":0,"hoofdrichting":0,"totaal":0,"locatie":"Bataviabrug"},{"uur5minuten":"7:00","datum":"2018-12-23","tegenrichting":2,"hoofdrichting":1,"totaal":3,"locatie":"Bataviabrug"},{"uur5minuten":"8:00","datum":"2018-12-23","tegenrichting":1,"hoofdrichting":3,"totaal":4,"locatie":"Bataviabrug"},{"uur5minuten":"9:00","datum":"2018-12-23","tegenrichting":5,"hoofdrichting":2,"totaal":7,"locatie":"Bataviabrug"},{"uur5minuten":"10:00","datum":"2018-12-23","tegenrichting":17,"hoofdrichting":7,"totaal":24,"locatie":"Bataviabrug"},{"uur5minuten":"11:00","datum":"2018-12-23","tegenrichting":7,"hoofdrichting":20,"totaal":27,"locatie":"Bataviabrug"},{"uur5minuten":"12:00","datum":"2018-12-23","tegenrichting":6,"hoofdrichting":13,"totaal":19,"locatie":"Bataviabrug"},{"uur5minuten":"13:00","datum":"2018-12-23","tegenrichting":9,"hoofdrichting":13,"totaal":22,"locatie":"Bataviabrug"},{"uur5minuten":"14:00","datum":"2018-12-23","tegenrichting":14,"hoofdrichting":6,"totaal":20,"locatie":"Bataviabrug"},{"uur5minuten":"15:00","datum":"2018-12-23","tegenrichting":19,"hoofdrichting":15,"totaal":34,"locatie":"Bataviabrug"},{"uur5minuten":"16:00","datum":"2018-12-23","tegenrichting":15,"hoofdrichting":14,"totaal":29,"locatie":"Bataviabrug"},{"uur5minuten":"17:00","datum":"2018-12-23","tegenrichting":13,"hoofdrichting":9,"totaal":22,"locatie":"Bataviabrug"},{"uur5minuten":"18:00","datum":"2018-12-23","tegenrichting":7,"hoofdrichting":5,"totaal":12,"locatie":"Bataviabrug"},{"uur5minuten":"19:00","datum":"2018-12-23","tegenrichting":5,"hoofdrichting":6,"totaal":11,"locatie":"Bataviabrug"},{"uur5minuten":"20:00","datum":"2018-12-23","tegenrichting":2,"hoofdrichting":3,"totaal":5,"locatie":"Bataviabrug"},{"uur5minuten":"21:00","datum":"2018-12-23","tegenrichting":9,"hoofdrichting":0,"totaal":9,"locatie":"Bataviabrug"},{"uur5minuten":"22:00","datum":"2018-12-23","tegenrichting":5,"hoofdrichting":1,"totaal":6,"locatie":"Bataviabrug"},{"uur5minuten":"23:00","datum":"2018-12-23","tegenrichting":1,"hoofdrichting":4,"totaal":5,"locatie":"Bataviabrug"},{"uur5minuten":"0:00","datum":"2018-12-24","tegenrichting":0,"hoofdrichting":4,"totaal":4,"locatie":"Bataviabrug"},{"uur5minuten":"1:00","datum":"2018-12-24","tegenrichting":1,"hoofdrichting":3,"totaal":4,"locatie":"Bataviabrug"},{"uur5minuten":"2:00","datum":"2018-12-24","tegenrichting":0,"hoofdrichting":2,"totaal":2,"locatie":"Bataviabrug"},{"uur5minuten":"3:00","datum":"2018-12-24","tegenrichting":2,"hoofdrichting":0,"totaal":2,"locatie":"Bataviabrug"},{"uur5minuten":"4:00","datum":"2018-12-24","tegenrichting":0,"hoofdrichting":1,"totaal":1,"locatie":"Bataviabrug"},{"uur5minuten":"5:00","datum":"2018-12-24","tegenrichting":0,"hoofdrichting":0,"totaal":0,"locatie":"Bataviabrug"},{"uur5minuten":"6:00","datum":"2018-12-24","tegenrichting":4,"hoofdrichting":4,"totaal":8,"locatie":"Bataviabrug"},{"uur5minuten":"7:00","datum":"2018-12-24","tegenrichting":8,"hoofdrichting":4,"totaal":12,"locatie":"Bataviabrug"},{"uur5minuten":"8:00","datum":"2018-12-24","tegenrichting":10,"hoofdrichting":11,"totaal":21,"locatie":"Bataviabrug"},{"uur5minuten":"9:00","datum":"2018-12-24","tegenrichting":19,"hoofdrichting":13,"totaal":32,"locatie":"Bataviabrug"},{"uur5minuten":"10:00","datum":"2018-12-24","tegenrichting":20,"hoofdrichting":16,"totaal":36,"locatie":"Bataviabrug"},{"uur5minuten":"11:00","datum":"2018-12-24","tegenrichting":19,"hoofdrichting":25,"totaal":44,"locatie":"Bataviabrug"},{"uur5minuten":"12:00","datum":"2018-12-24","tegenrichting":15,"hoofdrichting":26,"totaal":41,"locatie":"Bataviabrug"},{"uur5minuten":"13:00","datum":"2018-12-24","tegenrichting":17,"hoofdrichting":18,"totaal":35,"locatie":"Bataviabrug"},{"uur5minuten":"14:00","datum":"2018-12-24","tegenrichting":29,"hoofdrichting":24,"totaal":53,"locatie":"Bataviabrug"},{"uur5minuten":"15:00","datum":"2018-12-24","tegenrichting":20,"hoofdrichting":35,"totaal":55,"locatie":"Bataviabrug"},{"uur5minuten":"16:00","datum":"2018-12-24","tegenrichting":13,"hoofdrichting":25,"totaal":38,"locatie":"Bataviabrug"},{"uur5minuten":"17:00","datum":"2018-12-24","tegenrichting":17,"hoofdrichting":12,"totaal":29,"locatie":"Bataviabrug"},{"uur5minuten":"18:00","datum":"2018-12-24","tegenrichting":5,"hoofdrichting":12,"totaal":17,"locatie":"Bataviabrug"},{"uur5minuten":"19:00","datum":"2018-12-24","tegenrichting":7,"hoofdrichting":5,"totaal":12,"locatie":"Bataviabrug"},{"uur5minuten":"20:00","datum":"2018-12-24","tegenrichting":0,"hoofdrichting":3,"totaal":3,"locatie":"Bataviabrug"},{"uur5minuten":"21:00","datum":"2018-12-24","tegenrichting":1,"hoofdrichting":6,"totaal":7,"locatie":"Bataviabrug"},{"uur5minuten":"22:00","datum":"2018-12-24","tegenrichting":2,"hoofdrichting":1,"totaal":3,"locatie":"Bataviabrug"},{"uur5minuten":"23:00","datum":"2018-12-24","tegenrichting":2,"hoofdrichting":2,"totaal":4,"locatie":"Bataviabrug"},{"uur5minuten":"0:00","datum":"2018-12-25","tegenrichting":4,"hoofdrichting":2,"totaal":6,"locatie":"Bataviabrug"},{"uur5minuten":"1:00","datum":"2018-12-25","tegenrichting":1,"hoofdrichting":7,"totaal":8,"locatie":"Bataviabrug"},{"uur5minuten":"2:00","datum":"2018-12-25","tegenrichting":2,"hoofdrichting":0,"totaal":2,"locatie":"Bataviabrug"},{"uur5minuten":"3:00","datum":"2018-12-25","tegenrichting":1,"hoofdrichting":1,"totaal":2,"locatie":"Bataviabrug"},{"uur5minuten":"4:00","datum":"2018-12-25","tegenrichting":1,"hoofdrichting":0,"totaal":1,"locatie":"Bataviabrug"},{"uur5minuten":"5:00","datum":"2018-12-25","tegenrichting":0,"hoofdrichting":0,"totaal":0,"locatie":"Bataviabrug"},{"uur5minuten":"6:00","datum":"2018-12-25","tegenrichting":1,"hoofdrichting":2,"totaal":3,"locatie":"Bataviabrug"},{"uur5minuten":"7:00","datum":"2018-12-25","tegenrichting":2,"hoofdrichting":0,"totaal":2,"locatie":"Bataviabrug"},{"uur5minuten":"8:00","datum":"2018-12-25","tegenrichting":0,"hoofdrichting":0,"totaal":0,"locatie":"Bataviabrug"},{"uur5minuten":"9:00","datum":"2018-12-25","tegenrichting":1,"hoofdrichting":0,"totaal":1,"locatie":"Bataviabrug"},{"uur5minuten":"10:00","datum":"2018-12-25","tegenrichting":7,"hoofdrichting":9,"totaal":16,"locatie":"Bataviabrug"},{"uur5minuten":"11:00","datum":"2018-12-25","tegenrichting":7,"hoofdrichting":1,"totaal":8,"locatie":"Bataviabrug"},{"uur5minuten":"12:00","datum":"2018-12-25","tegenrichting":11,"hoofdrichting":11,"totaal":22,"locatie":"Bataviabrug"},{"uur5minuten":"13:00","datum":"2018-12-25","tegenrichting":10,"hoofdrichting":10,"totaal":20,"locatie":"Bataviabrug"},{"uur5minuten":"14:00","datum":"2018-12-25","tegenrichting":6,"hoofdrichting":7,"totaal":13,"locatie":"Bataviabrug"},{"uur5minuten":"15:00","datum":"2018-12-25","tegenrichting":21,"hoofdrichting":13,"totaal":34,"locatie":"Bataviabrug"},{"uur5minuten":"16:00","datum":"2018-12-25","tegenrichting":9,"hoofdrichting":5,"totaal":14,"locatie":"Bataviabrug"},{"uur5minuten":"17:00","datum":"2018-12-25","tegenrichting":3,"hoofdrichting":3,"totaal":6,"locatie":"Bataviabrug"},{"uur5minuten":"18:00","datum":"2018-12-25","tegenrichting":7,"hoofdrichting":14,"totaal":21,"locatie":"Bataviabrug"},{"uur5minuten":"19:00","datum":"2018-12-25","tegenrichting":5,"hoofdrichting":4,"totaal":9,"locatie":"Bataviabrug"},{"uur5minuten":"20:00","datum":"2018-12-25","tegenrichting":3,"hoofdrichting":3,"totaal":6,"locatie":"Bataviabrug"},{"uur5minuten":"21:00","datum":"2018-12-25","tegenrichting":3,"hoofdrichting":4,"totaal":7,"locatie":"Bataviabrug"},{"uur5minuten":"22:00","datum":"2018-12-25","tegenrichting":0,"hoofdrichting":1,"totaal":1,"locatie":"Bataviabrug"},{"uur5minuten":"23:00","datum":"2018-12-25","tegenrichting":7,"hoofdrichting":3,"totaal":10,"locatie":"Bataviabrug"},{"uur5minuten":"0:00","datum":"2018-12-26","tegenrichting":1,"hoofdrichting":0,"totaal":1,"locatie":"Bataviabrug"},{"uur5minuten":"1:00","datum":"2018-12-26","tegenrichting":5,"hoofdrichting":0,"totaal":5,"locatie":"Bataviabrug"},{"uur5minuten":"2:00","datum":"2018-12-26","tegenrichting":1,"hoofdrichting":2,"totaal":3,"locatie":"Bataviabrug"},{"uur5minuten":"3:00","datum":"2018-12-26","tegenrichting":0,"hoofdrichting":1,"totaal":1,"locatie":"Bataviabrug"},{"uur5minuten":"4:00","datum":"2018-12-26","tegenrichting":0,"hoofdrichting":0,"totaal":0,"locatie":"Bataviabrug"},{"uur5minuten":"5:00","datum":"2018-12-26","tegenrichting":1,"hoofdrichting":3,"totaal":4,"locatie":"Bataviabrug"},{"uur5minuten":"6:00","datum":"2018-12-26","tegenrichting":5,"hoofdrichting":3,"totaal":8,"locatie":"Bataviabrug"},{"uur5minuten":"7:00","datum":"2018-12-26","tegenrichting":10,"hoofdrichting":6,"totaal":16,"locatie":"Bataviabrug"},{"uur5minuten":"8:00","datum":"2018-12-26","tegenrichting":27,"hoofdrichting":13,"totaal":40,"locatie":"Bataviabrug"},{"uur5minuten":"9:00","datum":"2018-12-26","tegenrichting":19,"hoofdrichting":6,"totaal":25,"locatie":"Bataviabrug"},{"uur5minuten":"10:00","datum":"2018-12-26","tegenrichting":8,"hoofdrichting":17,"totaal":25,"locatie":"Bataviabrug"},{"uur5minuten":"11:00","datum":"2018-12-26","tegenrichting":21,"hoofdrichting":11,"totaal":32,"locatie":"Bataviabrug"},{"uur5minuten":"12:00","datum":"2018-12-26","tegenrichting":18,"hoofdrichting":14,"totaal":32,"locatie":"Bataviabrug"},{"uur5minuten":"13:00","datum":"2018-12-26","tegenrichting":16,"hoofdrichting":21,"totaal":37,"locatie":"Bataviabrug"},{"uur5minuten":"14:00","datum":"2018-12-26","tegenrichting":16,"hoofdrichting":10,"totaal":26,"locatie":"Bataviabrug"},{"uur5minuten":"15:00","datum":"2018-12-26","tegenrichting":11,"hoofdrichting":19,"totaal":30,"locatie":"Bataviabrug"},{"uur5minuten":"16:00","datum":"2018-12-26","tegenrichting":26,"hoofdrichting":22,"totaal":48,"locatie":"Bataviabrug"},{"uur5minuten":"17:00","datum":"2018-12-26","tegenrichting":12,"hoofdrichting":46,"totaal":58,"locatie":"Bataviabrug"},{"uur5minuten":"18:00","datum":"2018-12-26","tegenrichting":12,"hoofdrichting":24,"totaal":36,"locatie":"Bataviabrug"},{"uur5minuten":"19:00","datum":"2018-12-26","tegenrichting":23,"hoofdrichting":8,"totaal":31,"locatie":"Bataviabrug"},{"uur5minuten":"20:00","datum":"2018-12-26","tegenrichting":7,"hoofdrichting":4,"totaal":11,"locatie":"Bataviabrug"},{"uur5minuten":"21:00","datum":"2018-12-26","tegenrichting":3,"hoofdrichting":5,"totaal":8,"locatie":"Bataviabrug"},{"uur5minuten":"22:00","datum":"2018-12-26","tegenrichting":2,"hoofdrichting":8,"totaal":10,"locatie":"Bataviabrug"},{"uur5minuten":"23:00","datum":"2018-12-26","tegenrichting":1,"hoofdrichting":11,"totaal":12,"locatie":"Bataviabrug"},{"uur5minuten":"0:00","datum":"2018-12-27","tegenrichting":2,"hoofdrichting":7,"totaal":9,"locatie":"Bataviabrug"},{"uur5minuten":"1:00","datum":"2018-12-27","tegenrichting":1,"hoofdrichting":1,"totaal":2,"locatie":"Bataviabrug"},{"uur5minuten":"2:00","datum":"2018-12-27","tegenrichting":4,"hoofdrichting":2,"totaal":6,"locatie":"Bataviabrug"},{"uur5minuten":"3:00","datum":"2018-12-27","tegenrichting":1,"hoofdrichting":1,"totaal":2,"locatie":"Bataviabrug"},{"uur5minuten":"4:00","datum":"2018-12-27","tegenrichting":0,"hoofdrichting":0,"totaal":0,"locatie":"Bataviabrug"},{"uur5minuten":"5:00","datum":"2018-12-27","tegenrichting":2,"hoofdrichting":6,"totaal":8,"locatie":"Bataviabrug"},{"uur5minuten":"6:00","datum":"2018-12-27","tegenrichting":3,"hoofdrichting":4,"totaal":7,"locatie":"Bataviabrug"},{"uur5minuten":"7:00","datum":"2018-12-27","tegenrichting":7,"hoofdrichting":7,"totaal":14,"locatie":"Bataviabrug"},{"uur5minuten":"8:00","datum":"2018-12-27","tegenrichting":22,"hoofdrichting":12,"totaal":34,"locatie":"Bataviabrug"},{"uur5minuten":"9:00","datum":"2018-12-27","tegenrichting":19,"hoofdrichting":8,"totaal":27,"locatie":"Bataviabrug"},{"uur5minuten":"10:00","datum":"2018-12-27","tegenrichting":16,"hoofdrichting":5,"totaal":21,"locatie":"Bataviabrug"},{"uur5minuten":"11:00","datum":"2018-12-27","tegenrichting":15,"hoofdrichting":13,"totaal":28,"locatie":"Bataviabrug"},{"uur5minuten":"12:00","datum":"2018-12-27","tegenrichting":13,"hoofdrichting":15,"totaal":28,"locatie":"Bataviabrug"},{"uur5minuten":"13:00","datum":"2018-12-27","tegenrichting":17,"hoofdrichting":19,"totaal":36,"locatie":"Bataviabrug"},{"uur5minuten":"14:00","datum":"2018-12-27","tegenrichting":33,"hoofdrichting":17,"totaal":50,"locatie":"Bataviabrug"},{"uur5minuten":"15:00","datum":"2018-12-27","tegenrichting":33,"hoofdrichting":41,"totaal":74,"locatie":"Bataviabrug"},{"uur5minuten":"16:00","datum":"2018-12-27","tegenrichting":19,"hoofdrichting":32,"totaal":51,"locatie":"Bataviabrug"},{"uur5minuten":"17:00","datum":"2018-12-27","tegenrichting":24,"hoofdrichting":52,"totaal":76,"locatie":"Bataviabrug"},{"uur5minuten":"18:00","datum":"2018-12-27","tegenrichting":35,"hoofdrichting":21,"totaal":56,"locatie":"Bataviabrug"},{"uur5minuten":"19:00","datum":"2018-12-27","tegenrichting":21,"hoofdrichting":14,"totaal":35,"locatie":"Bataviabrug"},{"uur5minuten":"20:00","datum":"2018-12-27","tegenrichting":16,"hoofdrichting":14,"totaal":30,"locatie":"Bataviabrug"},{"uur5minuten":"21:00","datum":"2018-12-27","tegenrichting":11,"hoofdrichting":13,"totaal":24,"locatie":"Bataviabrug"},{"uur5minuten":"22:00","datum":"2018-12-27","tegenrichting":11,"hoofdrichting":14,"totaal":25,"locatie":"Bataviabrug"},{"uur5minuten":"23:00","datum":"2018-12-27","tegenrichting":2,"hoofdrichting":14,"totaal":16,"locatie":"Bataviabrug"},{"uur5minuten":"0:00","datum":"2018-12-28","tegenrichting":0,"hoofdrichting":5,"totaal":5,"locatie":"Bataviabrug"},{"uur5minuten":"1:00","datum":"2018-12-28","tegenrichting":1,"hoofdrichting":4,"totaal":5,"locatie":"Bataviabrug"},{"uur5minuten":"2:00","datum":"2018-12-28","tegenrichting":2,"hoofdrichting":1,"totaal":3,"locatie":"Bataviabrug"},{"uur5minuten":"3:00","datum":"2018-12-28","tegenrichting":2,"hoofdrichting":2,"totaal":4,"locatie":"Bataviabrug"},{"uur5minuten":"4:00","datum":"2018-12-28","tegenrichting":1,"hoofdrichting":1,"totaal":2,"locatie":"Bataviabrug"},{"uur5minuten":"5:00","datum":"2018-12-28","tegenrichting":1,"hoofdrichting":2,"totaal":3,"locatie":"Bataviabrug"},{"uur5minuten":"6:00","datum":"2018-12-28","tegenrichting":2,"hoofdrichting":1,"totaal":3,"locatie":"Bataviabrug"},{"uur5minuten":"7:00","datum":"2018-12-28","tegenrichting":10,"hoofdrichting":7,"totaal":17,"locatie":"Bataviabrug"},{"uur5minuten":"8:00","datum":"2018-12-28","tegenrichting":23,"hoofdrichting":9,"totaal":32,"locatie":"Bataviabrug"},{"uur5minuten":"9:00","datum":"2018-12-28","tegenrichting":13,"hoofdrichting":13,"totaal":26,"locatie":"Bataviabrug"},{"uur5minuten":"10:00","datum":"2018-12-28","tegenrichting":15,"hoofdrichting":8,"totaal":23,"locatie":"Bataviabrug"},{"uur5minuten":"11:00","datum":"2018-12-28","tegenrichting":21,"hoofdrichting":18,"totaal":39,"locatie":"Bataviabrug"},{"uur5minuten":"12:00","datum":"2018-12-28","tegenrichting":16,"hoofdrichting":22,"totaal":38,"locatie":"Bataviabrug"},{"uur5minuten":"13:00","datum":"2018-12-28","tegenrichting":15,"hoofdrichting":23,"totaal":38,"locatie":"Bataviabrug"},{"uur5minuten":"14:00","datum":"2018-12-28","tegenrichting":22,"hoofdrichting":13,"totaal":35,"locatie":"Bataviabrug"},{"uur5minuten":"15:00","datum":"2018-12-28","tegenrichting":17,"hoofdrichting":20,"totaal":37,"locatie":"Bataviabrug"},{"uur5minuten":"16:00","datum":"2018-12-28","tegenrichting":9,"hoofdrichting":25,"totaal":34,"locatie":"Bataviabrug"},{"uur5minuten":"17:00","datum":"2018-12-28","tegenrichting":23,"hoofdrichting":25,"totaal":48,"locatie":"Bataviabrug"},{"uur5minuten":"18:00","datum":"2018-12-28","tegenrichting":17,"hoofdrichting":24,"totaal":41,"locatie":"Bataviabrug"},{"uur5minuten":"19:00","datum":"2018-12-28","tegenrichting":14,"hoofdrichting":16,"totaal":30,"locatie":"Bataviabrug"},{"uur5minuten":"20:00","datum":"2018-12-28","tegenrichting":5,"hoofdrichting":10,"totaal":15,"locatie":"Bataviabrug"},{"uur5minuten":"21:00","datum":"2018-12-28","tegenrichting":5,"hoofdrichting":8,"totaal":13,"locatie":"Bataviabrug"},{"uur5minuten":"22:00","datum":"2018-12-28","tegenrichting":12,"hoofdrichting":6,"totaal":18,"locatie":"Bataviabrug"},{"uur5minuten":"23:00","datum":"2018-12-28","tegenrichting":4,"hoofdrichting":7,"totaal":11,"locatie":"Bataviabrug"},{"uur5minuten":"0:00","datum":"2018-12-29","tegenrichting":5,"hoofdrichting":4,"totaal":9,"locatie":"Bataviabrug"},{"uur5minuten":"1:00","datum":"2018-12-29","tegenrichting":1,"hoofdrichting":1,"totaal":2,"locatie":"Bataviabrug"},{"uur5minuten":"2:00","datum":"2018-12-29","tegenrichting":2,"hoofdrichting":2,"totaal":4,"locatie":"Bataviabrug"},{"uur5minuten":"3:00","datum":"2018-12-29","tegenrichting":1,"hoofdrichting":0,"totaal":1,"locatie":"Bataviabrug"},{"uur5minuten":"4:00","datum":"2018-12-29","tegenrichting":0,"hoofdrichting":1,"totaal":1,"locatie":"Bataviabrug"},{"uur5minuten":"5:00","datum":"2018-12-29","tegenrichting":1,"hoofdrichting":0,"totaal":1,"locatie":"Bataviabrug"},{"uur5minuten":"6:00","datum":"2018-12-29","tegenrichting":0,"hoofdrichting":0,"totaal":0,"locatie":"Bataviabrug"},{"uur5minuten":"7:00","datum":"2018-12-29","tegenrichting":4,"hoofdrichting":3,"totaal":7,"locatie":"Bataviabrug"},{"uur5minuten":"8:00","datum":"2018-12-29","tegenrichting":5,"hoofdrichting":8,"totaal":13,"locatie":"Bataviabrug"},{"uur5minuten":"9:00","datum":"2018-12-29","tegenrichting":13,"hoofdrichting":7,"totaal":20,"locatie":"Bataviabrug"},{"uur5minuten":"10:00","datum":"2018-12-29","tegenrichting":10,"hoofdrichting":16,"totaal":26,"locatie":"Bataviabrug"},{"uur5minuten":"11:00","datum":"2018-12-29","tegenrichting":21,"hoofdrichting":14,"totaal":35,"locatie":"Bataviabrug"},{"uur5minuten":"12:00","datum":"2018-12-29","tegenrichting":17,"hoofdrichting":20,"totaal":37,"locatie":"Bataviabrug"},{"uur5minuten":"13:00","datum":"2018-12-29","tegenrichting":15,"hoofdrichting":21,"totaal":36,"locatie":"Bataviabrug"},{"uur5minuten":"14:00","datum":"2018-12-29","tegenrichting":24,"hoofdrichting":16,"totaal":40,"locatie":"Bataviabrug"},{"uur5minuten":"15:00","datum":"2018-12-29","tegenrichting":19,"hoofdrichting":17,"totaal":36,"locatie":"Bataviabrug"},{"uur5minuten":"16:00","datum":"2018-12-29","tegenrichting":29,"hoofdrichting":35,"totaal":64,"locatie":"Bataviabrug"},{"uur5minuten":"17:00","datum":"2018-12-29","tegenrichting":14,"hoofdrichting":22,"totaal":36,"locatie":"Bataviabrug"},{"uur5minuten":"18:00","datum":"2018-12-29","tegenrichting":16,"hoofdrichting":25,"totaal":41,"locatie":"Bataviabrug"},{"uur5minuten":"19:00","datum":"2018-12-29","tegenrichting":16,"hoofdrichting":26,"totaal":42,"locatie":"Bataviabrug"},{"uur5minuten":"20:00","datum":"2018-12-29","tegenrichting":7,"hoofdrichting":4,"totaal":11,"locatie":"Bataviabrug"},{"uur5minuten":"21:00","datum":"2018-12-29","tegenrichting":10,"hoofdrichting":6,"totaal":16,"locatie":"Bataviabrug"},{"uur5minuten":"22:00","datum":"2018-12-29","tegenrichting":2,"hoofdrichting":10,"totaal":12,"locatie":"Bataviabrug"},{"uur5minuten":"23:00","datum":"2018-12-29","tegenrichting":8,"hoofdrichting":11,"totaal":19,"locatie":"Bataviabrug"},{"uur5minuten":"0:00","datum":"2018-12-30","tegenrichting":6,"hoofdrichting":6,"totaal":12,"locatie":"Bataviabrug"},{"uur5minuten":"1:00","datum":"2018-12-30","tegenrichting":6,"hoofdrichting":3,"totaal":9,"locatie":"Bataviabrug"},{"uur5minuten":"2:00","datum":"2018-12-30","tegenrichting":0,"hoofdrichting":3,"totaal":3,"locatie":"Bataviabrug"},{"uur5minuten":"3:00","datum":"2018-12-30","tegenrichting":1,"hoofdrichting":12,"totaal":13,"locatie":"Bataviabrug"},{"uur5minuten":"4:00","datum":"2018-12-30","tegenrichting":0,"hoofdrichting":2,"totaal":2,"locatie":"Bataviabrug"},{"uur5minuten":"5:00","datum":"2018-12-30","tegenrichting":0,"hoofdrichting":0,"totaal":0,"locatie":"Bataviabrug"},{"uur5minuten":"6:00","datum":"2018-12-30","tegenrichting":0,"hoofdrichting":0,"totaal":0,"locatie":"Bataviabrug"},{"uur5minuten":"7:00","datum":"2018-12-30","tegenrichting":4,"hoofdrichting":2,"totaal":6,"locatie":"Bataviabrug"},{"uur5minuten":"8:00","datum":"2018-12-30","tegenrichting":1,"hoofdrichting":4,"totaal":5,"locatie":"Bataviabrug"},{"uur5minuten":"9:00","datum":"2018-12-30","tegenrichting":10,"hoofdrichting":7,"totaal":17,"locatie":"Bataviabrug"},{"uur5minuten":"10:00","datum":"2018-12-30","tegenrichting":14,"hoofdrichting":6,"totaal":20,"locatie":"Bataviabrug"},{"uur5minuten":"11:00","datum":"2018-12-30","tegenrichting":14,"hoofdrichting":12,"totaal":26,"locatie":"Bataviabrug"},{"uur5minuten":"12:00","datum":"2018-12-30","tegenrichting":13,"hoofdrichting":24,"totaal":37,"locatie":"Bataviabrug"},{"uur5minuten":"13:00","datum":"2018-12-30","tegenrichting":13,"hoofdrichting":11,"totaal":24,"locatie":"Bataviabrug"},{"uur5minuten":"14:00","datum":"2018-12-30","tegenrichting":17,"hoofdrichting":16,"totaal":33,"locatie":"Bataviabrug"},{"uur5minuten":"15:00","datum":"2018-12-30","tegenrichting":16,"hoofdrichting":16,"totaal":32,"locatie":"Bataviabrug"},{"uur5minuten":"16:00","datum":"2018-12-30","tegenrichting":9,"hoofdrichting":16,"totaal":25,"locatie":"Bataviabrug"},{"uur5minuten":"17:00","datum":"2018-12-30","tegenrichting":12,"hoofdrichting":14,"totaal":26,"locatie":"Bataviabrug"},{"uur5minuten":"18:00","datum":"2018-12-30","tegenrichting":4,"hoofdrichting":13,"totaal":17,"locatie":"Bataviabrug"},{"uur5minuten":"19:00","datum":"2018-12-30","tegenrichting":17,"hoofdrichting":6,"totaal":23,"locatie":"Bataviabrug"},{"uur5minuten":"20:00","datum":"2018-12-30","tegenrichting":0,"hoofdrichting":6,"totaal":6,"locatie":"Bataviabrug"},{"uur5minuten":"21:00","datum":"2018-12-30","tegenrichting":2,"hoofdrichting":4,"totaal":6,"locatie":"Bataviabrug"},{"uur5minuten":"22:00","datum":"2018-12-30","tegenrichting":3,"hoofdrichting":7,"totaal":10,"locatie":"Bataviabrug"},{"uur5minuten":"23:00","datum":"2018-12-30","tegenrichting":4,"hoofdrichting":3,"totaal":7,"locatie":"Bataviabrug"},{"uur5minuten":"0:00","datum":"2018-12-31","tegenrichting":3,"hoofdrichting":3,"totaal":6,"locatie":"Bataviabrug"},{"uur5minuten":"1:00","datum":"2018-12-31","tegenrichting":2,"hoofdrichting":1,"totaal":3,"locatie":"Bataviabrug"},{"uur5minuten":"2:00","datum":"2018-12-31","tegenrichting":0,"hoofdrichting":1,"totaal":1,"locatie":"Bataviabrug"},{"uur5minuten":"3:00","datum":"2018-12-31","tegenrichting":0,"hoofdrichting":3,"totaal":3,"locatie":"Bataviabrug"},{"uur5minuten":"4:00","datum":"2018-12-31","tegenrichting":0,"hoofdrichting":1,"totaal":1,"locatie":"Bataviabrug"},{"uur5minuten":"5:00","datum":"2018-12-31","tegenrichting":0,"hoofdrichting":1,"totaal":1,"locatie":"Bataviabrug"},{"uur5minuten":"6:00","datum":"2018-12-31","tegenrichting":2,"hoofdrichting":6,"totaal":8,"locatie":"Bataviabrug"},{"uur5minuten":"7:00","datum":"2018-12-31","tegenrichting":6,"hoofdrichting":6,"totaal":12,"locatie":"Bataviabrug"},{"uur5minuten":"8:00","datum":"2018-12-31","tegenrichting":13,"hoofdrichting":9,"totaal":22,"locatie":"Bataviabrug"},{"uur5minuten":"9:00","datum":"2018-12-31","tegenrichting":8,"hoofdrichting":10,"totaal":18,"locatie":"Bataviabrug"},{"uur5minuten":"10:00","datum":"2018-12-31","tegenrichting":13,"hoofdrichting":15,"totaal":28,"locatie":"Bataviabrug"},{"uur5minuten":"11:00","datum":"2018-12-31","tegenrichting":17,"hoofdrichting":29,"totaal":46,"locatie":"Bataviabrug"},{"uur5minuten":"12:00","datum":"2018-12-31","tegenrichting":27,"hoofdrichting":28,"totaal":55,"locatie":"Bataviabrug"},{"uur5minuten":"13:00","datum":"2018-12-31","tegenrichting":22,"hoofdrichting":21,"totaal":43,"locatie":"Bataviabrug"},{"uur5minuten":"14:00","datum":"2018-12-31","tegenrichting":21,"hoofdrichting":29,"totaal":50,"locatie":"Bataviabrug"},{"uur5minuten":"15:00","datum":"2018-12-31","tegenrichting":22,"hoofdrichting":28,"totaal":50,"locatie":"Bataviabrug"},{"uur5minuten":"16:00","datum":"2018-12-31","tegenrichting":22,"hoofdrichting":27,"totaal":49,"locatie":"Bataviabrug"},{"uur5minuten":"17:00","datum":"2018-12-31","tegenrichting":11,"hoofdrichting":22,"totaal":33,"locatie":"Bataviabrug"},{"uur5minuten":"18:00","datum":"2018-12-31","tegenrichting":26,"hoofdrichting":14,"totaal":40,"locatie":"Bataviabrug"},{"uur5minuten":"19:00","datum":"2018-12-31","tegenrichting":9,"hoofdrichting":10,"totaal":19,"locatie":"Bataviabrug"},{"uur5minuten":"20:00","datum":"2018-12-31","tegenrichting":2,"hoofdrichting":8,"totaal":10,"locatie":"Bataviabrug"},{"uur5minuten":"21:00","datum":"2018-12-31","tegenrichting":6,"hoofdrichting":4,"totaal":10,"locatie":"Bataviabrug"},{"uur5minuten":"22:00","datum":"2018-12-31","tegenrichting":3,"hoofdrichting":7,"totaal":10,"locatie":"Bataviabrug"},{"uur5minuten":"23:00","datum":"2018-12-31","tegenrichting":4,"hoofdrichting":11,"totaal":15,"locatie":"Bataviabrug"}]